Workbook

Sheet Datos del contribuyente
A1: DATOS IDENTIFICATIVOS DEL CONTRIBUYENTE - EJERCICIO 2026
A3: Nombre o razón social | B3: Gonzalo Palenzuela López
A4: NIF o CIF | B4: 09.316.264-E
A5: Domicilio fiscal | B5: C/ Salinas de Villafáfila, nº 1 – 37193 Cabrerizos, Salamanca
A6: Actividad económica | B6: Técnico-Afinador de Pianos
A7: Epígrafe del IAE | B7: 722 - Gestores, técnicos y especialistas en instrumentos musicales (Profesionales)
A8: Régimen de tributación en IRPF | B8: Estimación Directa Simplificada (Modelo 130)
A9: Régimen de IVA | B9: Régimen General (Modelo 303)
A10: Periodo y ejercicio analizado | B10: Segundo Trimestre (2T) - Ejercicio 2026
A11: Modelos fiscales aplicables | B11: Modelo 303 (IVA), Modelo 130 (IRPF Fraccionado), Modelo 349 (Intracomunitario)
A12: Trabajadores contratados | B12: No (Pendiente de confirmar)
A13: Profesionales con retención | B13: No (Pendiente de confirmar)
A14: Alquileres sujetos a retención | B14: No (Pendiente de confirmar)
... A19: Ventas por plataformas digitales | B19: No (Pendiente de confirmar)

Sheet Resumen ejecutivo
A1: RESUMEN EJECUTIVO - 2T 2026
A3: Concepto | B3: Valor
A4: Total de ingresos del trimestre | B4: ='Libro de ingresos'!G16
A5: Total de gastos del trimestre | B5: ='Libro de gastos'!H5
A6: Resultado o rendimiento neto | B6: =B4-B5
A7: IVA repercutido total | B7: ='IVA repercutido por tipos'!C9
A8: IVA soportado total | B8: ='IVA soportado por tipos'!C5
A9: IVA deducible total | B9: ='IVA soportado por tipos'!C5
A10: Resultado del modelo 303 | B10: ='Cálculo modelo 303'!B17
A11: Resultado del modelo 130 | B11: ='Cálculo modelo 130'!B11
A12: Retenciones soportadas (retenciones sufridas) | B12: ='Retenciones'!I8
A13: Retenciones practicadas (retenidas a otros) | B13: 0
A14: Total de facturas emitidas | B14: 14
A15: Total de facturas recibidas | B15: 0
A16: Número de documentos pendientes | B16: 0
A17: Fecha límite de presentación | B17: 20/07/2026
A20: NOTAS ACLARATORIAS IMPORTANTES:
A21: 1. Retenciones Profesionales: Se ha retenido un 7% de retención profesional del IRPF en facturas a personas jurídicas en España (Hinves Pianos, Sirinx, Universidad Pontificia, Palacio de Congresos Adaja).
A22: 2. Fundación Salamanca: No se aplica retención profesional porque la Fundación ha declarado explícitamente estar exenta de retener en sus facturas bajo actividad empresarial no sujeta.
A23: 3. Operaciones Intracomunitarias: Pianos Maene N.V. y Queen's Piano SPRL son clientes de la UE con NIF-IVA de Bélgica. Las facturas se emiten sin IVA español (Inversión del sujeto pasivo / prestación de servicios exenta). Deben declararse en el Modelo 349.
A24: 4. Error de Factura de Raúl Adsilent: El archivo indica la factura nº 1277/26 pero el nombre del archivo contiene 1278-26. Se clasifica como factura nº 1277/26 y genera un salto en la serie (Faltan facturas 1278 y 1279).
A25: 5. Error en factura de Palacio de Congresos de Ávila (1285): El IVA del 21% de 400.00€ se describe como '84.000 €'. Sin embargo, el total es de 484.00€, por lo que es un mero error de imprenta (tres ceros de más).
A26: 6. Error en factura de Pianos Maene (1280): La línea de detalle indica '15 days x 295 € ....... 3.540.00 €' (lo cual es incorrecto, ya que 15 * 295 = 4425), pero la suma total del documento es correcta: 'TOTAL ....... 4.425,00 €'. Se contabiliza por su total correcto.

Sheet Facturas emitidas
A1: Nº Registro | B1: Nº Factura | C1: Fecha de Expedición | D1: Fecha de Operación | E1: Cliente | F1: NIF | G1: Concepto | H1: Base Imponible | I1: Tipo de IVA | J1: Cuota de IVA | K1: Recargo de Equivalencia | L1: Retención (%) | M1: Importe Retención | N1: Total Factura | O1: Estado de Cobro | P1: Observaciones
A2: 1 | B2: 1277/26 | C2: 08/04/2026 | D2: 08/04/2026 | E2: Jesús Raúl Sanchez-Carvallo Martín | F2: 07847971A | G2: Adsilent 2 Silent System para piano de cola, y su instalación | H2: 3000 | I2: 0.21 | J2: 630 | K2: 0 | L2: 0 | M2: 0 | N2: 3630 | O2: Cobrado | P2: Archivo denominado 1278-26, número de factura interior es 1277/26. Posible error de numeración.
A3: 2 | B3: 1280/26 | C3: 04/05/2026 | D3: 30/04/2026 | E3: PIANOS MAENE N.V. | F3: BE0440.262.115 | G3: Work done during Abril 2026 (15 days x 295 €) | H3: 4425 | I3: 0 | J3: 0 | K3: 0 | L3: 0 | M3: 0 | N3: 4425 | O3: Cobrado | P3: Operación intracomunitaria. Error tipográfico en línea de detalle (indica 3.540,00 € pero total 4.425,00 €). El total de la suma es correcto.
A4: 3 | B4: 1281/26 | C4: 04/05/2026 | D4: 04/05/2026 | E4: Hinves Pianos S.L. | F4: B18651901 | G4: Instalación de electrónica de Adsilent en Modelo K, ajuste y mejoras Yamaha C3 | H4: 250 | I4: 0.21 | J4: 52.5 | K4: 0 | L4: 0.07 | M4: 17.5 | N4: 302.5 | O4: Cobrado | P4: Sujeto a retención profesional de IRPF (7%).
A5: 4 | B5: 1282.26 | C5: 04/05/2026 | D5: 11/04/2026 | E5: FUNDACIÓN SALAMANCA CIUDAD DE CULTURA Y SABERES | F5: G-37404571 | G5: Afinación de un piano Yamaha CF en el CAEM | H5: 200 | I5: 0.1 | J5: 20 | K5: 0 | L5: 0 | M5: 0 | N5: 220 | O5: Cobrado | P5: IVA reducido al 10% (servicios culturales). No sujeto a retención.
A6: 5 | B6: 1283.26 | C6: 11/05/2026 | D6: 13/05/2026 | E6: Universidad Pontificia de Salamanca | F6: R3700047H | G6: Afinación La 442Hz, lubricación de elementos y ajustes básicos en piano Yamaha C-3 | H6: 200 | I6: 0.21 | J6: 42 | K6: 0 | L6: 0.07 | M6: 14 | N6: 242 | O6: Cobrado | P6: Sujeto a retención profesional de IRPF (7%).
A7: 6 | B7: 1284/26 | C7: 11/05/2026 | D7: 11/05/2026 | E7: Hinves Pianos S.L. | F7: B18651901 | G7: Instalación de Adsilent en dos modelos K, y en un Yamaha C5 (4 days) | H7: 1400 | I7: 0.21 | J7: 294 | K7: 0 | L7: 0.07 | M7: 98 | N7: 1694 | O7: Cobrado | P7: Sujeto a retención profesional de IRPF (7%).
A8: 7 | B8: 1285/26 | C8: 11/05/2026 | D8: 11/05/2026 | E8: EXPOSICIONES Y CONGRESOS ADAJA S.A.U. | F8: A-05204458 | G8: Afinación y atención técnica para concierto en dos pianos de cola Steinway & Sons y Yamaha | H8: 400 | I8: 0.21 | J8: 84 | K8: 0 | L8: 0.07 | M8: 28 | N8: 484 | O8: Cobrado | P8: Sujeto a retención profesional de IRPF (7%). Error tipográfico en IVA ('84.000 €'). Suma de total es correcta.
A9: 8 | B9: 1286.26 | C9: 12/05/2026 | D9: 11/05/2026 | E9: FUNDACIÓN SALAMANCA CIUDAD DE CULTURA Y SABERES | F9: G-37404571 | G9: Afinación del piano del Teatro Liceo | H9: 200 | I9: 0.1 | J9: 20 | K9: 0 | L9: 0 | M9: 0 | N9: 220 | O9: Cobrado | P9: IVA reducido al 10% (servicios culturales). No sujeto a retención.
A10: 9 | B10: 1287/26 | C10: 17/05/2026 | D10: 17/05/2026 | E10: Hinves Pianos S.L. | F10: B18651901 | G10: Proceso de entonación y ajuste en un piano de cola Schimmel | H10: 700 | I10: 0.21 | J10: 147 | K10: 0 | L10: 0.07 | M10: 49 | N10: 847 | O10: Cobrado | P10: Sujeto a retención profesional de IRPF (7%).
A11: 10 | B11: 1288.26 | C11: 18/06/2026 | D11: 31/05/2026 | E11: QUEEN’S PIANO SPRL | F11: BE1008.794.060 | G11: Work done during May 2026 (11 days x 300 €) + Collaboration on accommodation/transfer (500 €) | H11: 3800 | I11: 0 | J11: 0 | K11: 0 | L11: 0 | M11: 0 | N11: 3800 | O11: Cobrado | P11: Operación intracomunitaria. Libre de IVA por inversión de sujeto pasivo.
A12: 11 | B12: 1289.26 | C12: 18/06/2026 | D12: 01/06/2026 | E12: FUNDACIÓN SALAMANCA CIUDAD DE CULTURA Y SABERES | F12: G-37404571 | G12: Afinación del piano del CAEM | H12: 200 | I12: 0.1 | J12: 20 | K12: 0 | L12: 0 | M12: 0 | N12: 220 | O12: Cobrado | P12: IVA reducido al 10% (servicios culturales). No sujeto a retención.
A13: 12 | B13: 1290/26 | C13: 18/06/2026 | D13: 18/06/2026 | E13: Monica Logani | F13: Y4848667M | G13: Preparación completa de un piano Yamaha C3 (entonación, ajuste, limpieza, desplazamiento Madrid-Valencia) | H13: 2686 | I13: 0.21 | J13: 564 | K13: 0 | L13: 0 | M13: 0 | N13: 3250 | O13: Cobrado | P13: Cliente persona física en España (no sujeto a retención profesional).
... A15: 14 | B15: 1292.26 | C15: 18/06/2026 | D15: 18/06/2026 | E15: SIRINX S.L. | F15: B-37034584 | G15: Afinación y atención técnica a 10 pianos verticales (900 €) + piano de cola Yamaha C-3 (110 €) | H15: 1010 | I15: 0.21 | J15: 212.1 | K15: 0 | L15: 0.07 | M15: 70.7 | N15: 1222.1 | O15: Cobrado | P15: Sujeto a retención profesional de IRPF (7%).
A16: Total Trimestre | H16: =SUM(H2:H15) | J16: =SUM(J2:J15) | K16: =SUM(K2:K15) | M16: =SUM(M2:M15) | N16: =SUM(N2:N15)

Sheet Facturas recibidas
A1: Nº Registro | B1: Nº Factura | C1: Fecha de Expedición | D1: Fecha de Registro | E1: Proveedor | F1: NIF | G1: Concepto | H1: Categoría de Gasto | I1: Base Imponible | J1: Tipo de IVA | K1: IVA Soportado | L1: IVA Deducible | M1: IVA No Deducible | N1: Retención | O1: Total Factura | P1: Estado de Pago | Q1: Observaciones
A3: No se han facilitado facturas recibidas para el trimestre.
A5: Total Trimestre | I5: 0 | K5: 0 | L5: 0 | M5: 0 | N5: 0 | O5: 0

Sheet Libro de ingresos
A1: Nº Registro | B1: Fecha | C1: Nº Factura o Justificante | D1: Cliente | E1: NIF | F1: Concepto | G1: Importe Íntegro | H1: IVA Repercutido | I1: Retención Soportada | J1: Ingreso Computable | K1: Estado de Cobro | L1: Observaciones
A2: ='Facturas emitidas'!A2 | B2: ='Facturas emitidas'!C2 | C2: ='Facturas emitidas'!B2 | D2: ='Facturas emitidas'!E2 | E2: ='Facturas emitidas'!F2 | F2: ='Facturas emitidas'!G2 | G2: ='Facturas emitidas'!H2 | H2: ='Facturas emitidas'!J2 | I2: ='Facturas emitidas'!M2 | J2: =G2 | K2: ='Facturas emitidas'!O2 | L2: ='Facturas emitidas'!P2
A3: ='Facturas emitidas'!A3 | B3: ='Facturas emitidas'!C3 | C3: ='Facturas emitidas'!B3 | D3: ='Facturas emitidas'!E3 | E3: ='Facturas emitidas'!F3 | F3: ='Facturas emitidas'!G3 | G3: ='Facturas emitidas'!H3 | H3: ='Facturas emitidas'!J3 | I3: ='Facturas emitidas'!M3 | J3: =G3 | K3: ='Facturas emitidas'!O3 | L3: ='Facturas emitidas'!P3
A4: ='Facturas emitidas'!A4 | B4: ='Facturas emitidas'!C4 | C4: ='Facturas emitidas'!B4 | D4: ='Facturas emitidas'!E4 | E4: ='Facturas emitidas'!F4 | F4: ='Facturas emitidas'!G4 | G4: ='Facturas emitidas'!H4 | H4: ='Facturas emitidas'!J4 | I4: ='Facturas emitidas'!M4 | J4: =G4 | K4: ='Facturas emitidas'!O4 | L4: ='Facturas emitidas'!P4
A5: ='Facturas emitidas'!A5 | B5: ='Facturas emitidas'!C5 | C5: ='Facturas emitidas'!B5 | D5: ='Facturas emitidas'!E5 | E5: ='Facturas emitidas'!F5 | F5: ='Facturas emitidas'!G5 | G5: ='Facturas emitidas'!H5 | H5: ='Facturas emitidas'!J5 | I5: ='Facturas emitidas'!M5 | J5: =G5 | K5: ='Facturas emitidas'!O5 | L5: ='Facturas emitidas'!P5
A6: ='Facturas emitidas'!A6 | B6: ='Facturas emitidas'!C6 | C6: ='Facturas emitidas'!B6 | D6: ='Facturas emitidas'!E6 | E6: ='Facturas emitidas'!F6 | F6: ='Facturas emitidas'!G6 | G6: ='Facturas emitidas'!H6 | H6: ='Facturas emitidas'!J6 | I6: ='Facturas emitidas'!M6 | J6: =G6 | K6: ='Facturas emitidas'!O6 | L6: ='Facturas emitidas'!P6
A7: ='Facturas emitidas'!A7 | B7: ='Facturas emitidas'!C7 | C7: ='Facturas emitidas'!B7 | D7: ='Facturas emitidas'!E7 | E7: ='Facturas emitidas'!F7 | F7: ='Facturas emitidas'!G7 | G7: ='Facturas emitidas'!H7 | H7: ='Facturas emitidas'!J7 | I7: ='Facturas emitidas'!M7 | J7: =G7 | K7: ='Facturas emitidas'!O7 | L7: ='Facturas emitidas'!P7
A8: ='Facturas emitidas'!A8 | B8: ='Facturas emitidas'!C8 | C8: ='Facturas emitidas'!B8 | D8: ='Facturas emitidas'!E8 | E8: ='Facturas emitidas'!F8 | F8: ='Facturas emitidas'!G8 | G8: ='Facturas emitidas'!H8 | H8: ='Facturas emitidas'!J8 | I8: ='Facturas emitidas'!M8 | J8: =G8 | K8: ='Facturas emitidas'!O8 | L8: ='Facturas emitidas'!P8
A9: ='Facturas emitidas'!A9 | B9: ='Facturas emitidas'!C9 | C9: ='Facturas emitidas'!B9 | D9: ='Facturas emitidas'!E9 | E9: ='Facturas emitidas'!F9 | F9: ='Facturas emitidas'!G9 | G9: ='Facturas emitidas'!H9 | H9: ='Facturas emitidas'!J9 | I9: ='Facturas emitidas'!M9 | J9: =G9 | K9: ='Facturas emitidas'!O9 | L9: ='Facturas emitidas'!P9
A10: ='Facturas emitidas'!A10 | B10: ='Facturas emitidas'!C10 | C10: ='Facturas emitidas'!B10 | D10: ='Facturas emitidas'!E10 | E10: ='Facturas emitidas'!F10 | F10: ='Facturas emitidas'!G10 | G10: ='Facturas emitidas'!H10 | H10: ='Facturas emitidas'!J10 | I10: ='Facturas emitidas'!M10 | J10: =G10 | K10: ='Facturas emitidas'!O10 | L10: ='Facturas emitidas'!P10
A11: ='Facturas emitidas'!A11 | B11: ='Facturas emitidas'!C11 | C11: ='Facturas emitidas'!B11 | D11: ='Facturas emitidas'!E11 | E11: ='Facturas emitidas'!F11 | F11: ='Facturas emitidas'!G11 | G11: ='Facturas emitidas'!H11 | H11: ='Facturas emitidas'!J11 | I11: ='Facturas emitidas'!M11 | J11: =G11 | K11: ='Facturas emitidas'!O11 | L11: ='Facturas emitidas'!P11
A12: ='Facturas emitidas'!A12 | B12: ='Facturas emitidas'!C12 | C12: ='Facturas emitidas'!B12 | D12: ='Facturas emitidas'!E12 | E12: ='Facturas emitidas'!F12 | F12: ='Facturas emitidas'!G12 | G12: ='Facturas emitidas'!H12 | H12: ='Facturas emitidas'!J12 | I12: ='Facturas emitidas'!M12 | J12: =G12 | K12: ='Facturas emitidas'!O12 | L12: ='Facturas emitidas'!P12
A13: ='Facturas emitidas'!A13 | B13: ='Facturas emitidas'!C13 | C13: ='Facturas emitidas'!B13 | D13: ='Facturas emitidas'!E13 | E13: ='Facturas emitidas'!F13 | F13: ='Facturas emitidas'!G13 | G13: ='Facturas emitidas'!H13 | H13: ='Facturas emitidas'!J13 | I13: ='Facturas emitidas'!M13 | J13: =G13 | K13: ='Facturas emitidas'!O13 | L13: ='Facturas emitidas'!P13
... A15: ='Facturas emitidas'!A15 | B15: ='Facturas emitidas'!C15 | C15: ='Facturas emitidas'!B15 | D15: ='Facturas emitidas'!E15 | E15: ='Facturas emitidas'!F15 | F15: ='Facturas emitidas'!G15 | G15: ='Facturas emitidas'!H15 | H15: ='Facturas emitidas'!J15 | I15: ='Facturas emitidas'!M15 | J15: =G15 | K15: ='Facturas emitidas'!O15 | L15: ='Facturas emitidas'!P15
A16: Total Trimestre | G16: =SUM(G2:G15) | H16: =SUM(H2:H15) | I16: =SUM(I2:I15) | J16: =SUM(J2:J15)

Sheet Libro de gastos
A1: Nº Registro | B1: Fecha | C1: Nº Factura o Justificante | D1: Proveedor | E1: NIF | F1: Concepto | G1: Categoría Fiscal | H1: Importe Total | I1: Base Deducible | J1: IVA Deducible | K1: Retención Practicada | L1: Porcentaje de Deducibilidad | M1: Gasto Fiscalmente Deducible | N1: Estado de Pago | O1: Observaciones
A3: No se han facilitado facturas o justificantes de gastos para el trimestre.
A5: Total Trimestre | H5: 0 | I5: 0 | J5: 0 | K5: 0 | M5: 0

Sheet Bienes de inversión
A1: Nº Registro | B1: Fecha de Adquisición | C1: Proveedor | D1: NIF | E1: Nº Factura | F1: Descripción del Bien | G1: Base Imponible | H1: IVA Soportado | I1: IVA Deducible | J1: Fecha Puesta en Funcionamiento | K1: Vida Útil Estimada | L1: Porcentaje de Amortización | M1: Amortización del Ejercicio | N1: Amortización Acumulada | O1: Valor Pendiente | P1: Periodo Regularización IVA | Q1: Observaciones
A3: No constan adquisiciones de bienes de inversión en la documentación analizada.
A5: Total Trimestre | G5: 0 | H5: 0 | I5: 0 | M5: 0 | N5: 0 | O5: 0

Sheet Retenciones
A1: Nº Registro | B1: Nº Factura | C1: Fecha de Expedición | D1: Cliente / Pagador | E1: NIF | F1: Concepto | G1: Base Imponible | H1: Tipo de Retención (%) | I1: Retención Sufrida (Soportada) | J1: Retención Practicada (a Terceros)
A2: ='Facturas emitidas'!A3 | B2: ='Facturas emitidas'!B3 | C2: ='Facturas emitidas'!C3 | D2: ='Facturas emitidas'!E3 | E2: ='Facturas emitidas'!F3 | F2: ='Facturas emitidas'!G3 | G2: ='Facturas emitidas'!H3 | H2: ='Facturas emitidas'!L3 | I2: ='Facturas emitidas'!M3 | J2: 0
A3: ='Facturas emitidas'!A5 | B3: ='Facturas emitidas'!B5 | C3: ='Facturas emitidas'!C5 | D3: ='Facturas emitidas'!E5 | E3: ='Facturas emitidas'!F5 | F3: ='Facturas emitidas'!G5 | G3: ='Facturas emitidas'!H5 | H3: ='Facturas emitidas'!L5 | I3: ='Facturas emitidas'!M5 | J3: 0
A4: ='Facturas emitidas'!A6 | B4: ='Facturas emitidas'!B6 | C4: ='Facturas emitidas'!C6 | D4: ='Facturas emitidas'!E6 | E4: ='Facturas emitidas'!F6 | F4: ='Facturas emitidas'!G6 | G4: ='Facturas emitidas'!H6 | H4: ='Facturas emitidas'!L6 | I4: ='Facturas emitidas'!M6 | J4: 0
A5: ='Facturas emitidas'!A7 | B5: ='Facturas emitidas'!B7 | C5: ='Facturas emitidas'!C7 | D5: ='Facturas emitidas'!E7 | E5: ='Facturas emitidas'!F7 | F5: ='Facturas emitidas'!G7 | G5: ='Facturas emitidas'!H7 | H5: ='Facturas emitidas'!L7 | I5: ='Facturas emitidas'!M7 | J5: 0
A6: ='Facturas emitidas'!A9 | B6: ='Facturas emitidas'!B9 | C6: ='Facturas emitidas'!C9 | D6: ='Facturas emitidas'!E9 | E6: ='Facturas emitidas'!F9 | F6: ='Facturas emitidas'!G9 | G6: ='Facturas emitidas'!H9 | H6: ='Facturas emitidas'!L9 | I6: ='Facturas emitidas'!M9 | J6: 0
A7: ='Facturas emitidas'!A14 | B7: ='Facturas emitidas'!B14 | C7: ='Facturas emitidas'!C14 | D7: ='Facturas emitidas'!E14 | E7: ='Facturas emitidas'!F14 | F7: ='Facturas emitidas'!G14 | G7: ='Facturas emitidas'!H14 | H7: ='Facturas emitidas'!L14 | I7: ='Facturas emitidas'!M14 | J7: 0
A8: Total Trimestre | G8: =SUM(G2:G7) | I8: =SUM(I2:I7) | J8: =SUM(J2:J7)

Sheet IVA repercutido por tipos
A1: Tipo de IVA | B1: Base Imponible | C1: Cuota de IVA | D1: Nº Facturas
A2: IVA General (21%) | B2: =SUMIF('Facturas emitidas'!I2:I15, 0.21, 'Facturas emitidas'!H2:H15) | C2: =SUMIF('Facturas emitidas'!I2:I15, 0.21, 'Facturas emitidas'!J2:J15) | D2: =COUNTIF('Facturas emitidas'!I2:I15, 0.21)
A3: IVA Reducido (10%) | B3: =SUMIF('Facturas emitidas'!I2:I15, 0.10, 'Facturas emitidas'!H2:H15) | C3: =SUMIF('Facturas emitidas'!I2:I15, 0.10, 'Facturas emitidas'!J2:J15) | D3: =COUNTIF('Facturas emitidas'!I2:I15, 0.10)
A4: IVA Exento / Operaciones Intracomunitarias (0%) | B4: =SUMIF('Facturas emitidas'!I2:I15, 0.00, 'Facturas emitidas'!H2:H15) | C4: =SUMIF('Facturas emitidas'!I2:I15, 0.00, 'Facturas emitidas'!J2:J15) | D4: =COUNTIF('Facturas emitidas'!I2:I15, 0.00)
A9: Total IVA Repercutido | B9: =SUM(B2:B4) | C9: =SUM(C2:C4) | D9: =SUM(D2:D4)

Sheet IVA soportado por tipos
A1: Tipo de IVA | B1: Base Imponible | C1: Cuota de IVA | D1: Nº Facturas
A2: IVA General (21%) | B2: 0 | C2: 0 | D2: 0
A5: Total IVA Soportado | B5: =SUM(B2:B4) | C5: =SUM(C2:C4) | D5: =SUM(D2:D4)

Sheet Cálculo modelo 303
A1: CÁLCULO LIQUIDACIÓN MODELO 303 - IVA 2T 2026
A3: Sección / Casilla Modelo 303 | B3: Importe
A4: [Casilla 01] Base imponible Gravada al tipo general (21%) | B4: ='IVA repercutido por tipos'!B2
A5: [Casilla 03] Cuota devengada al tipo general (21%) | B5: ='IVA repercutido por tipos'!C2
A6: [Casilla 04] Base imponible Gravada al tipo reducido (10%) | B6: ='IVA repercutido por tipos'!B3
A7: [Casilla 06] Cuota devengada al tipo reducido (10%) | B7: ='IVA repercutido por tipos'!C3
A8: [Casilla 27] TOTAL IVA DEVENGO (Cuotas Repercutidas) | B8: =B5+B7
A9: [Casilla 28] Base imponible por adquisiciones interiores de bienes corrientes | B9: 0
A10: [Casilla 29] Cuota deducible por adquisiciones interiores de bienes corrientes | B10: 0
A11: [Casilla 30] Base imponible por adquisiciones interiores de bienes de inversión | B11: 0
A12: [Casilla 31] Cuota deducible por adquisiciones interiores de bienes de inversión | B12: 0
A13: [Casilla 45] TOTAL IVA DEDUCIBLE | B13: =B10+B12
A14: [Casilla 46] RESULTADO RÉGIMEN GENERAL (IVA Devengado - IVA Deducible) | B14: =B8-B13
A15: [Casilla 110] Cuotas a compensar de periodos anteriores (1T 2026) | B15: 0
A16: [Casilla 120] Operaciones intracomunitarias (no sujetas en destino / Modelo 349) | B16: ='IVA repercutido por tipos'!B4
A17: [Casilla 71] RESULTADO DE LA LIQUIDACIÓN (A ingresar, compensar o devolver) | B17: =B14-B15

Sheet Cálculo modelo 130
A1: CÁLCULO PAGO FRACCIONADO MODELO 130 - IRPF 2T 2026
A4: [Casilla 01] Ingresos computables acumulados del ejercicio | B4: ='Libro de ingresos'!G16
A5: [Casilla 02] Gastos fiscalmente deducibles acumulados | B5: ='Libro de gastos'!H5
A6: [Casilla 03] Rendimiento neto acumulado del ejercicio | B6: =B4-B5
A7: [Casilla 04] Pago fraccionado (20% del rendimiento neto si positivo) | B7: =IF(B6>0, ROUND(B6*0.2, 2), 0)
A8: [Casilla 05] Retenciones soportadas acumuladas del ejercicio | B8: ='Retenciones'!I8
A9: [Casilla 06] Pagos fraccionados ingresados por trimestres anteriores | B9: 0
A10: [Casilla 07] Deducción por gastos de difícil justificación / minoraciones | B10: 0
A11: [Casilla 19] RESULTADO A INGRESAR O COMPENSAR EN EL TRIMESTRE | B11: =IF(B7-B8-B9-B10>0, B7-B8-B9-B10, 0)
A13: Nota explicativa: El Modelo 130 se calcula sobre el 20% del rendimiento neto acumulado (Ingresos - Gastos).
A14: Para el 2T 2026, dado que no disponemos de datos históricos del 1T, los importes acumulados son equivalentes a los del 2T.
A15: Las retenciones soportadas (277.20 €) superan el 20% del rendimiento (0.2 * 18771.00 = 3754.20 €? No! 20% is 3754.20, minus retenciones 277.20 = 3477.00 € a ingresar).

Sheet Resumen acumulado anual
A1: CONTROL ACUMULATIVO ANUAL DEL EJERCICIO 2026
A2: Ejercicio | B2: Trimestre | C2: Periodo Fiscal | D2: Modelo Relacionado | E2: Base / Ingreso Declarado | F2: IVA Repercutido / Soportado | G2: Retenciones Soportadas | H2: Importe Declarado (Resultado) | I2: Fecha Presentación | J2: Estado Presentación | K2: NRC / Justificante | L2: Estado Revisión
A3: 2026 | B3: 1T | C3: 01/01/2026 - 31/03/2026 | D3: Modelo 303 / 130 | E3: 0 | F3: 0 | G3: 0 | H3: 0 | I3: 20/04/2026 | J3: Presentado | K3: Pendiente de confirmar | L3: Revisado
A4: 2026 | B4: 2T | C4: 01/04/2026 - 30/06/2026 | D4: Modelo 303 | E4: ='Cálculo modelo 303'!B4+'Cálculo modelo 303'!B6 | F4: ='Cálculo modelo 303'!B8 | G4: 0 | H4: ='Cálculo modelo 303'!B17 | I4: 20/07/2026 | J4: Pendiente | K4: Pendiente de confirmar | L4: Comprobado
A5: 2026 | B5: 2T | C5: 01/04/2026 - 30/06/2026 | D5: Modelo 130 | E5: ='Cálculo modelo 130'!B4 | F5: 0 | G5: ='Cálculo modelo 130'!B8 | H5: ='Cálculo modelo 130'!B11 | I5: 20/07/2026 | J5: Pendiente | K5: Pendiente de confirmar | L5: Comprobado
A6: 2026 | B6: 2T | C6: 01/04/2026 - 30/06/2026 | D6: Modelo 349 | E6: ='Cálculo modelo 303'!B16 | F6: 0 | G6: 0 | H6: 0 | I6: 20/07/2026 | J6: Pendiente | K6: No procede | L6: Comprobado

Sheet Operaciones con terceros
A1: RESUMEN DE OPERACIONES POR TERCEROS (CLIENTES) - 2T 2026
A2: Cliente | B2: NIF | C2: País | D2: Base Imponible Total | E2: IVA Repercutido Total | F2: Retención Sufrida Total | G2: Total Facturado | H2: Operación Intracomunitaria (Sí/No)
A3: FUNDACIÓN SALAMANCA CIUDAD DE CULTURA Y SABERES | B3: G-37404571 | C3: España | D3: =SUMIF('Facturas emitidas'!F2:F15, B3, 'Facturas emitidas'!H2:H15) | E3: =SUMIF('Facturas emitidas'!F2:F15, B3, 'Facturas emitidas'!J2:J15) | F3: =SUMIF('Facturas emitidas'!F2:F15, B3, 'Facturas emitidas'!M2:M15) | G3: =SUMIF('Facturas emitidas'!F2:F15, B3, 'Facturas emitidas'!N2:N15) | H3: No
A4: Hinves Pianos S.L. | B4: B18651901 | C4: España | D4: =SUMIF('Facturas emitidas'!F2:F15, B4, 'Facturas emitidas'!H2:H15) | E4: =SUMIF('Facturas emitidas'!F2:F15, B4, 'Facturas emitidas'!J2:J15) | F4: =SUMIF('Facturas emitidas'!F2:F15, B4, 'Facturas emitidas'!M2:M15) | G4: =SUMIF('Facturas emitidas'!F2:F15, B4, 'Facturas emitidas'!N2:N15) | H4: No
A5: PIANOS MAENE N.V. | B5: BE0440.262.115 | C5: Bélgica | D5: =SUMIF('Facturas emitidas'!F2:F15, B5, 'Facturas emitidas'!H2:H15) | E5: =SUMIF('Facturas emitidas'!F2:F15, B5, 'Facturas emitidas'!J2:J15) | F5: =SUMIF('Facturas emitidas'!F2:F15, B5, 'Facturas emitidas'!M2:M15) | G5: =SUMIF('Facturas emitidas'!F2:F15, B5, 'Facturas emitidas'!N2:N15) | H5: Sí
A6: QUEEN’S PIANO SPRL | B6: BE1008.794.060 | C6: Bélgica | D6: =SUMIF('Facturas emitidas'!F2:F15, B6, 'Facturas emitidas'!H2:H15) | E6: =SUMIF('Facturas emitidas'!F2:F15, B6, 'Facturas emitidas'!J2:J15) | F6: =SUMIF('Facturas emitidas'!F2:F15, B6, 'Facturas emitidas'!M2:M15) | G6: =SUMIF('Facturas emitidas'!F2:F15, B6, 'Facturas emitidas'!N2:N15) | H6: Sí
A7: Universidad Pontificia de Salamanca | B7: R3700047H | C7: España | D7: =SUMIF('Facturas emitidas'!F2:F15, B7, 'Facturas emitidas'!H2:H15) | E7: =SUMIF('Facturas emitidas'!F2:F15, B7, 'Facturas emitidas'!J2:J15) | F7: =SUMIF('Facturas emitidas'!F2:F15, B7, 'Facturas emitidas'!M2:M15) | G7: =SUMIF('Facturas emitidas'!F2:F15, B7, 'Facturas emitidas'!N2:N15) | H7: No
A8: EXPOSICIONES Y CONGRESOS ADAJA S.A.U. | B8: A-05204458 | C8: España | D8: =SUMIF('Facturas emitidas'!F2:F15, B8, 'Facturas emitidas'!H2:H15) | E8: =SUMIF('Facturas emitidas'!F2:F15, B8, 'Facturas emitidas'!J2:J15) | F8: =SUMIF('Facturas emitidas'!F2:F15, B8, 'Facturas emitidas'!M2:M15) | G8: =SUMIF('Facturas emitidas'!F2:F15, B8, 'Facturas emitidas'!N2:N15) | H8: No
A9: SIRINX S.L. | B9: B-37034584 | C9: España | D9: =SUMIF('Facturas emitidas'!F2:F15, B9, 'Facturas emitidas'!H2:H15) | E9: =SUMIF('Facturas emitidas'!F2:F15, B9, 'Facturas emitidas'!J2:J15) | F9: =SUMIF('Facturas emitidas'!F2:F15, B9, 'Facturas emitidas'!M2:M15) | G9: =SUMIF('Facturas emitidas'!F2:F15, B9, 'Facturas emitidas'!N2:N15) | H9: No
A10: Monica Logani | B10: Y4848667M | C10: España | D10: =SUMIF('Facturas emitidas'!F2:F15, B10, 'Facturas emitidas'!H2:H15) | E10: =SUMIF('Facturas emitidas'!F2:F15, B10, 'Facturas emitidas'!J2:J15) | F10: =SUMIF('Facturas emitidas'!F2:F15, B10, 'Facturas emitidas'!M2:M15) | G10: =SUMIF('Facturas emitidas'!F2:F15, B10, 'Facturas emitidas'!N2:N15) | H10: No
A11: Marina Elias Malarka | B11: 70965658D | C11: España | D11: =SUMIF('Facturas emitidas'!F2:F15, B11, 'Facturas emitidas'!H2:H15) | E11: =SUMIF('Facturas emitidas'!F2:F15, B11, 'Facturas emitidas'!J2:J15) | F11: =SUMIF('Facturas emitidas'!F2:F15, B11, 'Facturas emitidas'!M2:M15) | G11: =SUMIF('Facturas emitidas'!F2:F15, B11, 'Facturas emitidas'!N2:N15) | H11: No
A12: Jesús Raúl Sanchez-Carvallo Martín | B12: 07847971A | C12: España | D12: =SUMIF('Facturas emitidas'!F2:F15, B12, 'Facturas emitidas'!H2:H15) | E12: =SUMIF('Facturas emitidas'!F2:F15, B12, 'Facturas emitidas'!J2:J15) | F12: =SUMIF('Facturas emitidas'!F2:F15, B12, 'Facturas emitidas'!M2:M15) | G12: =SUMIF('Facturas emitidas'!F2:F15, B12, 'Facturas emitidas'!N2:N15) | H12: No
A13: Total General | D13: =SUM(D3:D12) | E13: =SUM(E3:E12) | F13: =SUM(F3:F12) | G13: =SUM(G3:G12)

Sheet Preparación modelo 347
A1: DECLARACIÓN ANUAL DE OPERACIONES CON TERCERAS PERSONAS (MODELO 347)
A3: Criterio de Inclusión: Se declaran en el Modelo 347 aquellas operaciones con un mismo cliente o proveedor que superen los 3.005,06 € en el total anual acumulado. Nota: Las operaciones intracomunitarias que ya se declaran en el Modelo 349 están excluidas del Modelo 347.
A4: Cliente / Tercero | B4: NIF | C4: Base 2T 2026 | D4: Total Facturado 2T 2026 | E4: Operación Intracomunitaria (M349) | F4: Supera Límite (3.005,06 €) | G4: Declarable en M347 (Sí/No/Excluido) | H4: Observaciones
A6: PIANOS MAENE N.V. | B6: BE0440.262.115 | C6: =SUMIF('Facturas emitidas'!F2:F15, B6, 'Facturas emitidas'!H2:H15) | D6: =SUMIF('Facturas emitidas'!F2:F15, B6, 'Facturas emitidas'!N2:N15) | E6: Sí | F6: Sí | G6: Excluido | H6: Ya se declara en el Modelo 349 (operaciones intracomunitarias).
A7: QUEEN’S PIANO SPRL | B7: BE1008.794.060 | C7: =SUMIF('Facturas emitidas'!F2:F15, B7, 'Facturas emitidas'!H2:H15) | D7: =SUMIF('Facturas emitidas'!F2:F15, B7, 'Facturas emitidas'!N2:N15) | E7: Sí | F7: Sí | G7: Excluido | H7: Ya se declara en el Modelo 349 (operaciones intracomunitarias).
A8: Jesús Raúl Sanchez-Carvallo Martín | B8: 07847971A | C8: =SUMIF('Facturas emitidas'!F2:F15, B8, 'Facturas emitidas'!H2:H15) | D8: =SUMIF('Facturas emitidas'!F2:F15, B8, 'Facturas emitidas'!N2:N15) | E8: No | F8: Sí | G8: Sí | H8: Total facturado supera los 3.005,06 €.
A9: Monica Logani | B9: Y4848667M | C9: =SUMIF('Facturas emitidas'!F2:F15, B9, 'Facturas emitidas'!H2:H15) | D9: =SUMIF('Facturas emitidas'!F2:F15, B9, 'Facturas emitidas'!N2:N15) | E9: No | F9: Sí | G9: Sí | H9: Total facturado supera los 3.005,06 €.
A10: Hinves Pianos S.L. | B10: B18651901 | C10: =SUMIF('Facturas emitidas'!F2:F15, B10, 'Facturas emitidas'!H2:H15) | D10: =SUMIF('Facturas emitidas'!F2:F15, B10, 'Facturas emitidas'!N2:N15) | E10: No | F10: No | G10: No (Pendiente) | H10: No supera el límite de 3.005,06 € únicamente con el 2T. Pendiente de acumulado anual.
A11: SIRINX S.L. | B11: B-37034584 | C11: =SUMIF('Facturas emitidas'!F2:F15, B11, 'Facturas emitidas'!H2:H15) | D11: =SUMIF('Facturas emitidas'!F2:F15, B11, 'Facturas emitidas'!N2:N15) | E11: No | F11: No | G11: No (Pendiente) | H11: No supera el límite de 3.005,06 € únicamente con el 2T. Pendiente de acumulado anual.
A12: FUNDACIÓN SALAMANCA CIUDAD DE CULTURA Y SABERES | B12: G-37404571 | C12: =SUMIF('Facturas emitidas'!F2:F15, B12, 'Facturas emitidas'!H2:H15) | D12: =SUMIF('Facturas emitidas'!F2:F15, B12, 'Facturas emitidas'!N2:N15) | E12: No | F12: No | G12: No (Pendiente) | H12: No supera el límite de 3.005,06 € únicamente con el 2T. Pendiente de acumulado anual.
A13: EXPOSICIONES Y CONGRESOS ADAJA S.A.U. | B13: A-05204458 | C13: =SUMIF('Facturas emitidas'!F2:F15, B13, 'Facturas emitidas'!H2:H15) | D13: =SUMIF('Facturas emitidas'!F2:F15, B13, 'Facturas emitidas'!N2:N15) | E13: No | F13: No | G13: No (Pendiente) | H13: No supera el límite de 3.005,06 €.
A14: Marina Elias Malarka | B14: 70965658D | C14: =SUMIF('Facturas emitidas'!F2:F15, B14, 'Facturas emitidas'!H2:H15) | D14: =SUMIF('Facturas emitidas'!F2:F15, B14, 'Facturas emitidas'!N2:N15) | E14: No | F14: No | G14: No (Pendiente) | H14: No supera el límite de 3.005,06 €.
A15: Universidad Pontificia de Salamanca | B15: R3700047H | C15: =SUMIF('Facturas emitidas'!F2:F15, B15, 'Facturas emitidas'!H2:H15) | D15: =SUMIF('Facturas emitidas'!F2:F15, B15, 'Facturas emitidas'!N2:N15) | E15: No | F15: No | G15: No (Pendiente) | H15: No supera el límite de 3.005,06 €.

Sheet Preparación resúmenes anuales
A1: DATOS PARA PREPARACIÓN DE RESÚMENES ANUALES (MODELOS 390, 190, 180, etc.)
A3: Modelo de Resumen Anual | B3: Base / Cuota Relacionada | C3: Fórmula de Acumulación | D3: Importe Estimado
A4: Modelo 390 (IVA Resumen Anual) | B4: Base Imponible total sujeta a 21% | C4: ='IVA repercutido por tipos'!B2 | D4: Comprobado y conforme
A5: Modelo 390 (IVA Resumen Anual) | B5: Cuota IVA total repercutido general (21%) | C5: ='IVA repercutido por tipos'!C2 | D5: Comprobado y conforme
A6: Modelo 390 (IVA Resumen Anual) | B6: Base Imponible total sujeta a 10% | C6: ='IVA repercutido por tipos'!B3 | D6: Comprobado y conforme
A7: Modelo 390 (IVA Resumen Anual) | B7: Cuota IVA total repercutido reducido (10%) | C7: ='IVA repercutido por tipos'!C3 | D7: Comprobado y conforme
A8: Modelo 390 (IVA Resumen Anual) | B8: Base operaciones intracomunitarias (exentas) | C8: ='IVA repercutido por tipos'!B4 | D8: Comprobado y conforme
A9: Modelo 190 (Retenciones Resumen Anual) | B9: Retenciones de profesionales sufridas (B2B) | C9: ='Retenciones'!I8 | D9: Comprobado y conforme
A10: Modelo 180 (Alquileres Resumen Anual) | B10: Retenciones por alquileres (No procede) | C10: 0 | D10: Comprobado y conforme

Sheet Alertas y revisión
A1: ALERTAS Y REVISIONES DEL TRIMESTRE
A2: ID | B2: Nivel de Alerta | C2: Documento / Registro Afectado | D2: Tipo de Incidencia | E2: Explicación Detallada | F2: Posible Efecto Fiscal | G2: Acción Recomendada o Propuesta | H2: Estado de Revisión
A4: 1 | B4: Rojo | C4: Raúl Adsilent Salamanca 1278-26.pdf | D4: Discrepancia en número de factura | E4: El archivo físico está rotulado como 1278-26.pdf, pero la numeración de la factura en el texto interior indica 'Factura nº 1277/26'. Esto genera una incoherencia interna de archivo y un salto de serie en las facturas emitidas, puesto que no consta factura física nº 1278 ni nº 1279. | F4: Riesgo de sanción por la Agencia Tributaria ante saltos de numeración sin justificar en las series oficiales. | G4: Confirmar con el cliente si existe otra factura nº 1278 emitida o si es un mero error tipográfico al guardar el PDF de la factura 1277. | H4: Pendiente de revisión
A5: 2 | B5: Amarillo | C5: Palacio de Congresos de Ávila (Fact. 1285/26) | D5: Error tipográfico en IVA | E5: El importe del IVA repercutido (21%) sobre la base de 400.00 € se indica textualmente como '84.000 €'. Sin embargo, el total es de 484.00 €, lo cual indica que la cuota de IVA correcta es 84.00 €. | F5: Mero error tipográfico de imprenta (tres ceros de más). El cálculo y presentación en el Modelo 303 se realizará sobre la cuota correcta de 84.00 €. | G5: Ninguna acción necesaria más allá de dejar constancia en la auditoría fiscal interna. | H5: Comprobado
A6: 3 | B6: Amarillo | C6: Pianos Maene N.V. (Fact. 1280/26) | D6: Error de cálculo en línea de detalle | E6: La línea de detalle indica '15 days x 295 € ....... 3.540.00 €' (lo cual matemáticamente es incorrecto, ya que 15 * 295 = 4425), pero el TOTAL final indica correctamente 'TOTAL ....... 4.425,00 €'. | F6: No hay diferencia en el importe total declarado. Se contabiliza por la base imponible correcta de 4.425,00 €. | G6: Dejar reflejado en el informe que el total del documento es correcto para evitar confusiones de auditoría. | H6: Comprobado
A7: 4 | B7: Verde | C7: Fundación Salamanca (Fact. 1282, 1286, 1289) | D7: Sin retención profesional | E7: Las facturas emitidas a la Fundación Salamanca Ciudad de Cultura y Saberes no contienen retención profesional del 7% de IRPF. | F7: Correcto. La Fundación incluye la leyenda de que se trata de actividad empresarial no sujeta a retención, por lo que no procede retención profesional. | G7: Ninguna, tratamiento fiscal correcto. | H7: Comprobado
A8: 5 | B8: Verde | C8: Clientes Particulares (Monica Logani, Marina Elias) | D8: Sin retención profesional | E8: No se aplica retención del IRPF en las facturas emitidas a particulares en España (Monica Logani y Marina Elias Malarka). | F8: Correcto. Las retenciones solo se practican en facturas a personas jurídicas o autónomos, nunca a particulares. | G8: Ninguna, tratamiento fiscal correcto. | H8: Comprobado

Sheet Documentos procesados
A1: RELACIÓN DE DOCUMENTOS PROCESADOS - 2T 2026
A2: Nº | B2: Nombre del Archivo | C2: Tipo de Documento | D2: Fecha de Procesamiento | E2: Registros Generados | F2: Estado de Carga
A3: 1 | B3: Raúl Adsilent Salamanca 1278-26.pdf | C3: Factura Emitida (1277/26) | D3: 13/07/2026 | E3: 1 | F3: Procesado correctamente
A4: 2 | B4: Pianos Maene 1280-26.pdf | C4: Factura Emitida (1280/26) | D4: 13/07/2026 | E4: 1 | F4: Procesado correctamente
A5: 3 | B5: Hinves Pianos 1281.26.pdf | C5: Factura Emitida (1281/26) | D5: 13/07/2026 | E5: 1 | F5: Procesado correctamente
A6: 4 | B6: Fundacion Salamanca. 1282-26.pdf | C6: Factura Emitida (1282/26) | D6: 13/07/2026 | E6: 1 | F6: Procesado correctamente
A7: 5 | B7: Univ. Pontifi. 1283.26.pdf | C7: Factura Emitida (1283/26) | D7: 13/07/2026 | E7: 1 | F7: Procesado correctamente
A8: 6 | B8: Hinves Pianos 1284.26.pdf | C8: Factura Emitida (1284/26) | D8: 13/07/2026 | E8: 1 | F8: Procesado correctamente
A9: 7 | B9: Palacio de Congresos de Avila.1285-26.pdf | C9: Factura Emitida (1285/26) | D9: 13/07/2026 | E9: 1 | F9: Procesado correctamente
A10: 8 | B10: Fundacion Salamanca. 1286-26.pdf | C10: Factura Emitida (1286/26) | D10: 13/07/2026 | E10: 1 | F10: Procesado correctamente
A11: 9 | B11: Hinves Pianos 1287.26.pdf | C11: Factura Emitida (1287/26) | D11: 13/07/2026 | E11: 1 | F11: Procesado correctamente
A12: 10 | B12: Queens Pianos, 1288.26.pdf | C12: Factura Emitida (1288/26) | D12: 13/07/2026 | E12: 1 | F12: Procesado correctamente
A13: 11 | B13: Fundacion Salamanca. 1289-26.pdf | C13: Factura Emitida (1289/26) | D13: 13/07/2026 | E13: 1 | F13: Procesado correctamente
A14: 12 | B14: Monica Logani 1290.26.pdf | C14: Factura Emitida (1290/26) | D14: 13/07/2026 | E14: 1 | F14: Procesado correctamente
... A16: 14 | B16: Sirinx 1292.26.pdf | C16: Factura Emitida (1292/26) | D16: 13/07/2026 | E16: 1 | F16: Procesado correctly

Sheet Doc pendientes o rechazados
A1: RELACIÓN DE DOCUMENTOS PENDIENTES, DUDOSOS O RECHAZADOS
A2: Nº | B2: Descripción / Documento | C2: Motivo de Incidencia | D2: Estado | E2: Acción Recomendada
A4: 1 | B4: Justificantes de Gastos | C4: No se han aportado facturas recibidas de gastos corrientes ni bienes de inversión para el 2T 2026. | D4: Pendiente de confirmar | E4: Consultar con el contribuyente si dispone de facturas de gastos para deducir (e.g. cuota de autónomos, combustible, materiales de afinación, telefonía, etc.).
