Workbook

Sheet Resumen ejecutivo
A1: Resumen ejecutivo fiscal - ANA BELEN FEIJOO VIDUEIRA - 2T 2026
A3: Cliente | B3: ANA BELEN FEIJOO VIDUEIRA
A4: NIF | B4: 34975084L
A5: Periodo objetivo | B5: 2T 2026
A6: Documentos procesados | B6: 122
A7: Documentos incluidos 2T | B7: 117
A8: Documentos fuera 2T | B8: 6
A9: Documentos pendientes revisión | B9: 36
A10: Retenciones detectadas | B10: =SUM('Facturas recibidas'!S2:S150)
B11: =SUMIFS('Facturas recibidas'!K2:K150, 'Facturas recibidas'!X2:X150, "Sí") | C11: =SUMIFS('Facturas recibidas'!M2:M150, 'Facturas recibidas'!X2:X150, "Sí") | E11: =SUMIFS('Facturas recibidas'!N2:N150, 'Facturas recibidas'!X2:X150, "Sí")
A12: Indicador 2T | B12: Importe/Base | C12: IVA Soportado | D12: IVA Devengado ISP | E12: Total | F12: Notas
A13: Facturas nacionales con IVA 21% | B13: ='IVA por tipos'!C3 + 280.00 | C13: ='IVA por tipos'!E3 + 58.80 | D13: 178.8 | E13: =B13+C13 | F13: Incluye AUCTANE, CIFRA, Amazon, Amazon Ads España, Eurogrow, IONOS, Finetwork, Digi, Navapack, PlasticForte, Leroy Merlin, alquiler, portes 21% y facturas mixtas
A14: Gastos sin IVA nacionales / exentos | B14: ='IVA por tipos'!C4 | C14: 0 | D14: 14.66 | E14: =B14 | F14: TGSS autónomos, comunidad, seguros de préstamo y otros sin IVA; revisar deducibilidad/afectación
A15: Intracomunitarias bienes | B15: ='IVA por tipos'!C5 | C15: 67.79 | D15: ='IVA por tipos'!F5 | E15: =B15 | F15: ARTEVASI Portugal y VIVEIROS CULTIFLOR; ISP estimada al 21%
A16: Servicios intracomunitarios recibidos | B16: ='IVA por tipos'!C6 | D16: ='IVA por tipos'!F6 | E16: =B16 | F16: Amazon Ads Italia/Francia y Stripe Irlanda con reverse charge; ISP estimada al 21%
A17: Facturas nacionales con IVA 10% | B17: ='IVA por tipos'!C7 | C17: ='IVA por tipos'!E7 | D17: 214.46 | E17: =B17+C17 | F17: Iberdrola, Siro, Projar y Ricardo Terán; revisar afectación/deducibilidad donde proceda
A18: Proveedor China / importación | B18: ='IVA por tipos'!C9 | E18: =B18 | F18: Alibaba/Wuhan China; no se incorpora IVA importación sin DUA
A19: Total gastos conocidos 2T | B19: =SUM(B13:B18) | C19: =SUM(C13,C17) | D19: =SUM(D15:D16) | E19: =SUM(E13:E18) | F19: Incluye todas las facturas y documentos del 2T; excluye importes fuera de periodo; ISP UE queda como estimación
A20: Notas de prudencia fiscal
A21: Notas de prudencia fiscal
A22: 1. No se inventan datos: los importes no legibles o no convertidos se dejan pendientes de revisión.
A23: 2. Los documentos de enero, febrero y marzo aparecen en el libro, pero no se suman al 2T salvo decisión profesional distinta.
A24: 3. Operaciones UE/China/EE.UU. requieren revisión de ROI, inversión del sujeto pasivo, DUA, justificantes de pago y tipo de cambio.
A25: 4. Este archivo corresponde solo a ANA BELEN FEIJOO VIDUEIRA; no mezclar con otros clientes.

Sheet Facturas recibidas
A1: Cliente | B1: NIF cliente | C1: Periodo | D1: Fecha | E1: Nº factura/documento | F1: Proveedor | G1: NIF/CIF proveedor | H1: País | I1: Tipo operación | J1: Descripción | K1: Base imponible EUR | L1: % IVA | M1: IVA soportado EUR | N1: Total EUR | O1: Moneda original | P1: Importe original | Q1: Deducibilidad | R1: % Retención | S1: Retención EUR | T1: Clasificación fiscal | U1: Estado revisión | V1: Observaciones | W1: Documento origen | X1: Incluye en 2T
A2: ANA BELEN FEIJOO VIDUEIRA | B2: 34975084L | C2: 2T 2026 | D2: 46028 | E2: LX2251204 | F2: JINHUA LANXIANG IMPORT & EXPORT CO., LTD | G2: Pendiente | H2: China | I2: Importación de bienes / compra exterior | J2: Bolsas para chalecos, factura comercial EXW | K2: 997.27 | L2: 0 | M2: 0 | N2: 997.27 | O2: USD | P2: 1125 | Q2: 1 | R2: 0 | S2: 0 | T2: Compra exterior sin IVA español | U2: Pendiente de revisión | V2: Importe EUR indicado como pagado en el documento. Falta DUA/IVA importación y tipo de cambio justificativo. | W2: 001_2T 2026_ALIBABA-COMPRA BOLSAS PARA CHALECOS.pdf | X2: No
A3: ANA BELEN FEIJOO VIDUEIRA | B3: 34975084L | C3: 2T 2026 | D3: 46149 | E3: CN20260507ES | F3: WUHAN BOSA SHIPPING CO., LTD | G3: Pendiente | H3: China | I3: Servicios transporte/logística exterior DDP | J3: Envío chalecos y cubre motos por mar DDP | L3: 0 | O3: USD | P3: 2718.1 | Q3: 1 | R3: 0 | S3: 0 | T3: Servicio/proveedor no UE sin IVA español | U3: Pendiente de revisión | V3: Falta conversión EUR, factura/justificante de pago y posible tratamiento de importación/DUA por condición DDP. | W3: 002_2T 2026_Alibaba-Envio Chalecos+Cubre motos-Ana Feijoo---2026.05.03.pdf | X3: Sí
A4: ANA BELEN FEIJOO VIDUEIRA | B4: 34975084L | C4: 2T 2026 | D4: 46129 | E4: FA 2026/11490 | F4: ARTEVASI, S.A. | G4: PT507747879 | H4: Portugal | I4: Adquisición intracomunitaria de bienes | J4: Platos y artículos de plástico. Exento art. 14 RITI | K4: 333.36 | L4: 0 | M4: 0 | N4: 333.36 | O4: EUR | P4: 333.36 | Q4: 1 | R4: 0 | S4: 0 | T4: Operación intracomunitaria con inversión sujeto pasivo | U4: Pendiente de revisión | V4: Proveedor UE con IVA 0. Requiere autorrepercusión y deducción si procede; base a declarar en operaciones intracomunitarias. | W4: 003_2T 2026_ARTEVASI FA_2026_11490.pdf | X4: Sí
A5: ANA BELEN FEIJOO VIDUEIRA | B5: 34975084L | C5: 2T 2026 | D5: 46119 | E5: ES26FC02107187 | F5: AUCTANE S.L.U | G5: ESB83357863 | H5: España | I5: Compra/servicio nacional con IVA | J5: Correos Express - Paq 24 | K5: 4.89 | L5: 0.21 | M5: 1.03 | N5: 5.92 | O5: EUR | P5: 5.92 | Q5: 1 | R5: 0 | S5: 0 | T5: Gasto con IVA soportado nacional | U5: Revisado | V5: Factura española con IVA 21%. | W5: 004_2T 2026_AUCTANE ES26FC02107187.pdf | X5: Sí
A6: ANA BELEN FEIJOO VIDUEIRA | B6: 34975084L | C6: 2T 2026 | D6: 46142 | E6: Adeudo TGSS 04/2026 | F6: TGSS - R.E. Autónomos | G6: ES75005Q2827003A | H6: España | I6: Cuota autónomos / organismo público | J6: Cotización RETA abril 2026 | K6: 299.57 | L6: 0 | M6: 0 | N6: 299.57 | O6: EUR | P6: 299.57 | Q6: 1 | R6: 0 | S6: 0 | T6: Gasto deducible sin IVA | U6: Revisado | V6: Cargo bancario de cuota de autónomos; sin IVA. | W6: 005_2T 2026_Autonomos Abril.pdf | X6: Sí
A7: ANA BELEN FEIJOO VIDUEIRA | B7: 34975084L | C7: 2T 2026 | D7: 46171 | E7: Adeudo TGSS 05/2026 | F7: TGSS - R.E. Autónomos | G7: ES75005Q2827003A | H7: España | I7: Cuota autónomos / organismo público | J7: Cotización RETA mayo 2026 | K7: 299.57 | L7: 0 | M7: 0 | N7: 299.57 | O7: EUR | P7: 299.57 | Q7: 1 | R7: 0 | S7: 0 | T7: Gasto deducible sin IVA | U7: Revisado | V7: Cargo bancario de cuota de autónomos; sin IVA. | W7: 006_2T 2026_Autonomos Mayo.pdf | X7: Sí
A8: ANA BELEN FEIJOO VIDUEIRA | B8: 34975084L | C8: 2T 2026 | D8: 46081 | E8: BIZPYPT5-0010 | F8: OpenAI Ireland Limited | G8: IE4143435AH | H8: Irlanda | I8: Servicio intracomunitario recibido | J8: ChatGPT Plus Subscription | K8: 19.01 | L8: 0 | M8: 0 | N8: 19.01 | O8: EUR | P8: 19.01 | Q8: 1 | R8: 0 | S8: 0 | T8: Servicio intracomunitario con inversión sujeto pasivo | U8: Fuera de periodo 2T | V8: Factura 0% reverse charge. Pertenece a febrero, no a 2T. | W8: 007_2T 2026_CHATGPT FERBERO Invoice-BIZPYPT5-0010.pdf | X8: No
A9: ANA BELEN FEIJOO VIDUEIRA | B9: 34975084L | C9: 2T 2026 | D9: 46079 | E9: FDE174A8-0028 | F9: OpenAI OpCo, LLC | G9: EU OSS VAT EU372041333 | H9: Estados Unidos / OSS UE | I9: Servicio digital con IVA OSS | J9: ChatGPT Plus Subscription Feb-Mar | K9: 16.95 | L9: 0.21 | M9: 3.56 | N9: 20.51 | O9: USD | P9: 24.2 | Q9: 1 | R9: 0 | S9: 0 | T9: Servicio digital con IVA español vía OSS | U9: Fuera de periodo 2T | V9: Base EUR calculada como IVA EUR / 21% porque solo consta IVA en euros. Revisar soporte de pago/tipo cambio. | W9: 008_2T 2026_CHATGPT Invoice-FDE174A8-0028.pdf | X9: No
A10: ANA BELEN FEIJOO VIDUEIRA | B10: 34975084L | C10: 2T 2026 | D10: 46107 | E10: FDE174A8-0029 | F10: OpenAI OpCo, LLC | G10: EU OSS VAT EU372041333 | H10: Estados Unidos / OSS UE | I10: Servicio digital con IVA OSS | J10: ChatGPT Plus Subscription Mar-Apr | K10: 17.33 | L10: 0.21 | M10: 3.64 | N10: 20.97 | O10: USD | P10: 24.2 | Q10: 1 | R10: 0 | S10: 0 | T10: Servicio digital con IVA español vía OSS | U10: Fuera de periodo 2T | V10: Base EUR calculada como IVA EUR / 21% porque solo consta IVA en euros. Revisar soporte de pago/tipo cambio. | W10: 009_2T 2026_CHATGPT Invoice-FDE174A8-0029.pdf | X10: No
A11: ANA BELEN FEIJOO VIDUEIRA | B11: 34975084L | C11: 2T 2026 | D11: 46143 | E11: CE261701849 | F11: C.I.F.R.A., S.L. | G11: B30668420 | H11: España | I11: Compra nacional con IVA | J11: Chaleco reflectante Visibility 600 ud. | K11: 531 | L11: 0.21 | M11: 111.51 | N11: 642.51 | O11: EUR | P11: 642.51 | Q11: 1 | R11: 0 | S11: 0 | T11: Compra mercaderías con IVA soportado | U11: Revisado | V11: Factura nacional con IVA 21%. | W11: 010_2T 2026_CIFRA CE261701849.pdf | X11: Sí
A12: ANA BELEN FEIJOO VIDUEIRA | B12: 34975084L | C12: 2T 2026 | D12: 46156 | E12: CE261704792 | F12: C.I.F.R.A., S.L. | G12: B30668420 | H12: España | I12: Compra nacional con IVA | J12: Chaleco reflectante Visibility 600 ud. | K12: 531 | L12: 0.21 | M12: 111.51 | N12: 642.51 | O12: EUR | P12: 642.51 | Q12: 1 | R12: 0 | S12: 0 | T12: Compra mercaderías con IVA soportado | U12: Revisado | V12: Factura nacional con IVA 21%. | W12: 011_2T 2026_CIFRA CE261704792.pdf | X12: Sí
A13: ANA BELEN FEIJOO VIDUEIRA | B13: 34975084L | C13: 2T 2026 | D13: 46169 | E13: CE261708106 | F13: C.I.F.R.A., S.L. | G13: B30668420 | H13: España | I13: Compra nacional con IVA | J13: Chaleco reflectante Visibility 600 ud. | K13: 531 | L13: 0.21 | M13: 111.51 | N13: 642.51 | O13: EUR | P13: 642.51 | Q13: 1 | R13: 0 | S13: 0 | T13: Compra mercaderías con IVA soportado | U13: Revisado | V13: Factura nacional con IVA 21%. | W13: 012_2T 2026_CIFRA CE261708106.pdf | X13: Sí
A14: ANA BELEN FEIJOO VIDUEIRA | B14: 34975084L | C14: 2T 2026 | D14: 46142 | E14: ES-AEU-2026-291575 | F14: Amazon EU S.à r.l., Sucursal en España | G14: ESW0184081H | H14: España | I14: Servicio nacional con IVA | J14: Tarifas de logística de Amazon | K14: 5383.74 | L14: 0.21 | M14: 1130.58 | N14: 6514.32 | O14: EUR | P14: 6514.32 | Q14: 1 | R14: 0 | S14: 0 | T14: Gasto con IVA soportado nacional | U14: Revisado | V14: Factura fiscal española con IVA 21%. | W14: 013_2T 2026_ES-AEU-2026-291575.pdf | X14: Sí
A15: ANA BELEN FEIJOO VIDUEIRA | B15: 34975084L | C15: 2T 2026 | D15: 46142 | E15: ES-AEU-2026-291599 | F15: Amazon EU S.à r.l., Sucursal en España | G15: ESW0184081H | H15: España | I15: Servicio nacional con IVA | J15: Tarifas de vender en Amazon | K15: 1509.6 | L15: 0.21 | M15: 317.02 | N15: 1826.62 | O15: EUR | P15: 1826.62 | Q15: 1 | R15: 0 | S15: 0 | T15: Gasto con IVA soportado nacional | U15: Revisado | V15: Factura fiscal española con IVA 21%. | W15: 014_2T 2026_ES-AEU-2026-291599.pdf | X15: Sí
... A56: ANA BELEN FEIJOO VIDUEIRA | B56: 34975084L | C56: 2T 2026 | D56: 46146 | E56: 26209102 | F56: ALBERO FORTE COMPOSITE, S.L.U. / PlasticForte | G56: B54620182 | H56: España | I56: Compra nacional con IVA | J56: Macetas decorativas y macetas PS | K56: 501.09 | L56: 0.21 | M56: 105.23 | N56: 606.32 | O56: EUR | P56: 606.32 | Q56: 1 | R56: 0 | S56: 0 | T56: Compra de mercancía con IVA soportado nacional | U56: Revisado | V56: Factura de mercancía al 21%. Incluye aportación SCRAP informativa. | W56: 058_2T 2026_PLASTICFORTE-FRA ANA BELEN FEIJOO.pdf | X56: Sí
A57: ANA BELEN FEIJOO VIDUEIRA | B57: 34975084L | C57: 2T 2026 | D57: 46142 | E57: FN26-04152 | F57: COMERCIAL PROJAR S.A. | G57: A46217923 | H57: España | I57: Compra nacional con IVA mixto | J57: Perlita 3-9 mm 100L y transporte | K57: 289.33 | M57: 35.09 | N57: 324.42 | O57: EUR | P57: 324.42 | Q57: 1 | R57: 0 | S57: 0 | T57: Compra de mercancía con IVA soportado mixto 10%/21% | U57: Revisado | V57: Base 233,33 € al 10% (IVA 23,33 €) y base 56,00 € al 21% (IVA 11,76 €). | W57: 059_2T 2026_PROJAR Factura venta FN26-04152.pdf | X57: Sí
A58: ANA BELEN FEIJOO VIDUEIRA | B58: 34975084L | C58: 2T 2026 | D58: 46133 | E58: WB/1272 | F58: RICARDO TERÁN S.L. | G58: B32162364 | H58: España | I58: Compra nacional con IVA mixto | J58: Turba rubia fardos 250L y mensajería | K58: 125.77 | M58: 14.62 | N58: 140.39 | O58: EUR | P58: 140.39 | Q58: 1 | R58: 0 | S58: 0 | T58: Compra de mercancía con IVA soportado mixto 10%/21% | U58: Revisado | V58: Base 107,27 € al 10% (IVA 10,73 €) y base 18,50 € al 21% (IVA 3,89 €). | W58: 060_2T 2026_RICARDO TERAN WB0000001272 ANA BELEN FEIJOO VIDUEIRA.PDF | X58: Sí
A59: ANA BELEN FEIJOO VIDUEIRA | B59: 34975084L | C59: 2T 2026 | D59: 46148 | E59: WB/1293 | F59: RICARDO TERÁN S.L. | G59: B32162364 | H59: España | I59: Compra nacional con IVA mixto | J59: Tierra orquídeas 5L y mensajería | K59: 42.17 | M59: 4.76 | N59: 46.93 | O59: EUR | P59: 46.93 | Q59: 1 | R59: 0 | S59: 0 | T59: Compra de mercancía con IVA soportado mixto 10%/21% | U59: Revisado | V59: Base 37,27 € al 10% (IVA 3,73 €) y base 4,90 € al 21% (IVA 1,03 €). | W59: 061_2T 2026_RICARDO TERAN WB0000001293 ANA BELEN FEIJOO VIDUEIRA.PDF | X59: Sí
A60: ANA BELEN FEIJOO VIDUEIRA | B60: 34975084L | C60: 2T 2026 | D60: 46120 | E60: Adeudo seguro 08/04/2026 | F60: Mutua Madrileña Automovilista | G60: ES16501V28027118 | H60: España | I60: Seguro / operación exenta | J60: Seguro coche - adeudo directo | K60: 103.24 | L60: 0 | M60: 0 | N60: 103.24 | O60: EUR | P60: 103.24 | Q60: 1 | R60: 0 | S60: 0 | T60: Seguro exento sin IVA | U60: Pendiente de revisión | V60: Justificante bancario de seguro. Revisar afectación del vehículo a la actividad y deducibilidad del gasto. | W60: 062_2T 2026_Seguro COche-b7e9a011-8f89-4a2f-bc68-efce6fb25377.pdf | X60: Sí
A61: ANA BELEN FEIJOO VIDUEIRA | B61: 34975084L | C61: 2T 2026 | D61: 46156 | E61: B 260556 | F61: Leal e Soares España, S.L. / SIRO | G61: B15839475 | H61: España | I61: Compra nacional con IVA | J61: Siro Orquídeas Epífitas 5L | K61: 466.56 | L61: 0.1 | M61: 46.66 | N61: 513.22 | O61: EUR | P61: 513.22 | Q61: 1 | R61: 0 | S61: 0 | T61: Compra de mercancía con IVA soportado nacional 10% | U61: Revisado | V61: Factura de mercancía al 10%. | W61: 063_2T 2026_SIRO FAB260556.pdf | X61: Sí
A62: ANA BELEN FEIJOO VIDUEIRA | B62: 34975084L | C62: 2T 2026 | D62: 46147 | E62: 8489491A-0017 | F62: MENTORING AMZ GROUP LLC | G62: Pendiente | H62: Estados Unidos | I62: Servicio no UE recibido | J62: Club TPP Elite | K62: 25 | L62: 0 | M62: 0 | N62: 25 | O62: EUR | P62: 25 | Q62: 1 | R62: 0 | S62: 0 | T62: Servicio de proveedor no UE sin IVA español | U62: Pendiente de revisión | V62: Proveedor de EE.UU. sin IVA. Revisar posible inversión del sujeto pasivo/servicio B2B y justificante de afectación a la actividad. | W62: 064_2T 2026_TPP Invoice-8489491A-0017.pdf | X62: Sí
A63: ANA BELEN FEIJOO VIDUEIRA | B63: 34975084L | C63: 2T 2026 | D63: 46146 | E63: R-26-000117/1 | F63: CDAD PROP CAMINO CANEIRO 12 | G63: ES03000H32165342 | H63: España | I63: Gasto comunidad / sin IVA | J63: Comunidad propietarios Camino Caneiro 12 - recibo mayo 2026 | K63: 140 | L63: 0 | M63: 0 | N63: 140 | O63: EUR | P63: 140 | Q63: 1 | R63: 0 | S63: 0 | T63: Gasto sin IVA / comunidad | U63: Pendiente de revisión | V63: Justificante bancario. Revisar afectación del inmueble/actividad y si procede deducibilidad fiscal. | W63: 065_2T 2026_COMUNIDAD ABRIL.pdf | X63: Sí
A64: ANA BELEN FEIJOO VIDUEIRA | B64: 34975084L | C64: 2T 2026 | D64: 46174 | E64: R-26-000143/1 | F64: CDAD PROP CAMINO CANEIRO 12 | G64: ES03000H32165342 | H64: España | I64: Gasto comunidad / sin IVA | J64: Comunidad propietarios Camino Caneiro 12 - recibo junio 2026 | K64: 132 | L64: 0 | M64: 0 | N64: 132 | O64: EUR | P64: 132 | Q64: 1 | R64: 0 | S64: 0 | T64: Gasto sin IVA / comunidad | U64: Pendiente de revisión | V64: Justificante bancario. Revisar afectación del inmueble/actividad y si procede deducibilidad fiscal. | W64: 066_2T 2026_COMUNIDAD MAYO.pdf | X64: Sí
A65: ANA BELEN FEIJOO VIDUEIRA | B65: 34975084L | C65: 2T 2026 | D65: 46196 | E65: DGFC2617513172 | F65: DIGI Spain Telecom, S.A.U. | G65: A84919760 | H65: España | I65: Servicio nacional con IVA | J65: Fibra SMART 500Mb local alquilado - periodo 03/06/2026-12/06/2026 | K65: 2.67 | L65: 0.21 | M65: 0.56 | N65: 3.23 | O65: EUR | P65: 3.23 | Q65: 1 | R65: 0 | S65: 0 | T65: Gasto con IVA soportado nacional | U65: Revisado | V65: Factura de telecomunicaciones del local alquilado con IVA 21%. | W65: 067_2T 2026_DIGI LOCAL ALQUILADO DGFC2617513172.pdf | X65: Sí
A66: ANA BELEN FEIJOO VIDUEIRA | B66: 34975084L | C66: 2T 2026 | D66: 46189 | E66: CU2024268240 | F66: COMPRAS SEGURAS 2015 S.L.U. / Eurogrow | G66: B05247226 | H66: España | I66: Compra nacional con IVA | J66: Vermiculita 100L y productos promocionales | K66: 54.03 | L66: 0.21 | M66: 11.35 | N66: 65.38 | O66: EUR | P66: 65.38 | Q66: 1 | R66: 0 | S66: 0 | T66: Compra/gasto con IVA soportado nacional | U66: Pendiente de revisión | V66: Factura con IVA 21%. Revisar afectación de productos a la actividad. | W66: 068_2T 2026_EUROGROW CU2024268240.pdf | X66: Sí
A67: ANA BELEN FEIJOO VIDUEIRA | B67: 34975084L | C67: 2T 2026 | D67: 46199 | E67: Q 14190 | F67: FASAWORLD S.L. / Quecartucho | G67: B64713662 | H67: España | I67: Compra nacional con IVA | J67: Brother DK22205 cinta continua compatible | K67: 50.7 | L67: 0.21 | M67: 10.65 | N67: 61.35 | O67: EUR | P67: 61.35 | Q67: 1 | R67: 0 | S67: 0 | T67: Gasto con IVA soportado nacional | U67: Revisado | V67: Factura española con IVA 21%. | W67: 069_2T 2026_FASAWOL-QUECARTUCHO 2026-Q-14190.PDF | X67: Sí
A68: ANA BELEN FEIJOO VIDUEIRA | B68: 34975084L | C68: 2T 2026 | D68: 46143 | E68: CNP2601497180 | F68: WEWI MOBILE S.L. / Finetwork | G68: B54865845 | H68: España | I68: Servicio nacional con IVA | J68: Telefonía/fibra abril 2026 | K68: 35.29 | L68: 0.21 | M68: 7.41 | N68: 42.7 | O68: EUR | P68: 42.7 | Q68: 1 | R68: 0 | S68: 0 | T68: Gasto con IVA soportado nacional | U68: Pendiente de revisión | V68: Telecomunicaciones en domicilio. Revisar afectación/deducibilidad antes de presentar. | W68: 070_2T 2026_FINETWORK Factura_Abril 2026.pdf | X68: Sí
A69: ANA BELEN FEIJOO VIDUEIRA | B69: 34975084L | C69: 2T 2026 | D69: 46174 | E69: CNP2601864214 | F69: WEWI MOBILE S.L. / Finetwork | G69: B54865845 | H69: España | I69: Servicio nacional con IVA | J69: Telefonía/fibra mayo 2026 | K69: 32.14 | L69: 0.21 | M69: 6.75 | N69: 38.89 | O69: EUR | P69: 38.89 | Q69: 1 | R69: 0 | S69: 0 | T69: Gasto con IVA soportado nacional | U69: Pendiente de revisión | V69: Telecomunicaciones en domicilio. Revisar afectación/deducibilidad antes de presentar. | W69: 071_2T 2026_FINETWORK Factura_Mayo 2026.pdf | X69: Sí
A70: ANA BELEN FEIJOO VIDUEIRA | B70: 34975084L | C70: 2T 2026 | D70: 46204 | E70: CNP2602186099 | F70: WEWI MOBILE S.L. / Finetwork | G70: B54865845 | H70: España | I70: Servicio nacional con IVA | J70: Telefonía/fibra junio 2026; factura emitida 01/07/2026 | K70: 32.14 | L70: 0.21 | M70: 6.75 | N70: 38.89 | O70: EUR | P70: 38.89 | Q70: 1 | R70: 0 | S70: 0 | T70: Gasto con IVA soportado nacional | U70: Pendiente de revisión | V70: Factura emitida 01/07 por servicio de junio. Revisar criterio de imputación/declaración en 2T. | W70: 072_2T 2026_FINETWORK Factura_Junio 2026.pdf | X70: Sí
A71: ANA BELEN FEIJOO VIDUEIRA | B71: 34975084L | C71: 2T 2026 | D71: 46199 | E71: 202786679384 | F71: IONOS Cloud S.L.U. | G71: B85049435 | H71: España | I71: Servicio nacional con IVA | J71: IONOS antivirus premium e HiDrive Business | K71: 8.5 | L71: 0.21 | M71: 1.79 | N71: 10.29 | O71: EUR | P71: 10.29 | Q71: 1 | R71: 0 | S71: 0 | T71: Gasto con IVA soportado nacional | U71: Revisado | V71: Factura española con IVA 21%. | W71: 073_2T 2026_IONOS Factura_2026-06-26_202786679384.pdf | X71: Sí
... A125: ANA BELEN FEIJOO VIDUEIRA | B125: 34975084L | C125: 2T 2026 | D125: 46203 | E125: ES-CN-AEU-2026-155131 | F125: Amazon EU S.à r.l., Sucursal en España | G125: ESW0184081H | H125: España | I125: Rectificación de factura nacional (negativa) | J125: Tarifas reembolsadas | K125: -3.85 | L125: 0 | M125: 0 | N125: -3.85 | O125: EUR | P125: -3.85 | Q125: 1 | R125: 0 | S125: 0 | T125: Operación no sujeta/exenta sin IVA | U125: Revisado | V125: Nota de crédito de tarifas de logística de Amazon exenta. | W125: ES-CN-AEU-2026-155131.pdf | X125: Sí

Sheet Facturas emitidas
A1: Facturas emitidas - cliente ANA BELEN FEIJOO VIDUEIRA
A3: Fecha | B3: Nº factura | C3: Cliente/Destinatario | D3: Base EUR | E3: IVA EUR | F3: Total EUR | G3: Retención EUR | H3: Estado
A4: 46142 | B4: RESUMEN_AMAZON_ES_202604_21 | C4: Ventas Península 21% - Clientes Varios (España) | D4: 13795.05 | E4: 2899.11 | F4: 16694.16 | G4: 0 | H4: Revisado (Agregado)
A5: 46142 | B5: RESUMEN_AMAZON_ES_202604_00 | C5: Ventas Canarias 0% (Exentas) - Clientes Varios (España) | D5: 53.23 | E5: 0 | F5: 53.23 | G5: 0 | H5: Revisado (Agregado)
A6: 46142 | B6: RESUMEN_AMAZON_PT_202604_23 | C6: Ventas Particulares 23% - Clientes Varios (Portugal) | D6: 444.09 | E6: 102.19 | F6: 546.28 | G6: 0 | H6: Revisado (Agregado - OSS)
A7: 46142 | B7: RESUMEN_AMAZON_PT_202604_00 | C7: Ventas Empresas Intracomunitarias - Clientes Varios (Portugal) | D7: 37.73 | E7: 0 | F7: 37.73 | G7: 0 | H7: Revisado (Agregado - exento ROI)
A8: 46142 | B8: RESUMEN_AMAZON_FR_202604_20 | C8: Ventas Particulares 20% - Clientes Varios (Francia) | D8: 473.31 | E8: 94.66 | F8: 567.97 | G8: 0 | H8: Revisado (Agregado - OSS)
A9: 46142 | B9: RESUMEN_AMAZON_FR_202604_00 | C9: Ventas Empresas Intracomunitarias - Clientes Varios (Francia) | D9: 0.43 | E9: 0 | F9: 0.43 | G9: 0 | H9: Revisado (Agregado - exento ROI)
A10: 46142 | B10: RESUMEN_AMAZON_IT_202604_22 | C10: Ventas Particulares 22% - Clientes Varios (Italia) | D10: 69.24 | E10: 15.23 | F10: 84.47 | G10: 0 | H10: Revisado (Agregado - OSS)
A11: 46142 | B11: RESUMEN_AMAZON_LU_202604_17 | C11: Ventas Particulares 17% - Clientes Varios (Luxemburgo) | D11: 20.84 | E11: 3.54 | F11: 24.38 | G11: 0 | H11: Revisado (Agregado - OSS)
A12: 46173 | B12: RESUMEN_AMAZON_ES_202605_21 | C12: Ventas Península 21% - Clientes Varios (España) | D12: 14512.34 | E12: 3050.26 | F12: 17562.6 | G12: 0 | H12: Revisado (Agregado)
A13: 46173 | B13: RESUMEN_AMAZON_ES_202605_10 | C13: Ventas Península IVA Reducido 10% - Clientes Varios (España) | D13: 1557.65 | E13: 155.72 | F13: 1713.37 | G13: 0 | H13: Revisado (Agregado)
A14: 46173 | B14: RESUMEN_AMAZON_ES_202605_00 | C14: Ventas Canarias 0% (Exentas) - Clientes Varios (España) | D14: 9.11 | E14: 0 | F14: 9.11 | G14: 0 | H14: Revisado (Agregado)
A15: 46173 | B15: RESUMEN_AMAZON_PT_202605_23 | C15: Ventas Particulares 23% - Clientes Varios (Portugal) | D15: 487.43 | E15: 112.17 | F15: 599.6 | G15: 0 | H15: Revisado (Agregado - OSS)
... A36: 46203 | B36: RESUMEN_AMAZON_BE_202606_21 | C36: Ventas Particulares 21% - Clientes Varios (Bélgica) | D36: 13.59 | E36: 2.85 | F36: 16.44 | G36: 0 | H36: Revisado (Agregado - OSS)

Sheet Retenciones
A1: Retenciones detectadas
A3: Tipo | B3: Base | C3: % Retención | D3: Importe retención | E3: Modelo | F3: Documento | G3: Observaciones
A4: Alquiler | B4: =SUMIFS('Facturas recibidas'!K2:K150, 'Facturas recibidas'!X2:X150, "Sí", 'Facturas recibidas'!T2:T150, "Alquiler de local comercial sujeto a retención") | C4: 0.19 | D4: =SUMIFS('Facturas recibidas'!S2:S150, 'Facturas recibidas'!X2:X150, "Sí", 'Facturas recibidas'!T2:T150, "Alquiler de local comercial sujeto a retención") | E4: 115 | F4: Alquiler JUNIO 03-26 ANA BELEN FEIJOO.pdf | G4: Retención de alquiler de Rosa Fernández Da Bouza

Sheet IVA por tipos
A1: IVA por tipos y naturaleza de operación - 2T 2026
C2: =SUMIFS('Facturas recibidas'!K2:K150, 'Facturas recibidas'!X2:X150, "Sí") | E2: =SUMIFS('Facturas recibidas'!M2:M150, 'Facturas recibidas'!X2:X150, "Sí") | G2: =SUMIFS('Facturas recibidas'!N2:N150, 'Facturas recibidas'!X2:X150, "Sí")
A3: IVA nacional 21% | B3: Incluye documentos con IVA 21% y fecha 01/04-30/06 | C3: =SUMIFS('Facturas recibidas'!K2:K150, 'Facturas recibidas'!X2:X150, "Sí", 'Facturas recibidas'!L2:L150, 0.21, 'Facturas recibidas'!T2:T150, "<>Alquiler de local comercial sujeto a retención") | D3: 0.21 | E3: =SUMIFS('Facturas recibidas'!M2:M150, 'Facturas recibidas'!X2:X150, "Sí", 'Facturas recibidas'!L2:L150, 0.21, 'Facturas recibidas'!T2:T150, "<>Alquiler de local comercial sujeto a retención") | F3: 0 | G3: =SUMIFS('Facturas recibidas'!N2:N150, 'Facturas recibidas'!X2:X150, "Sí", 'Facturas recibidas'!L2:L150, 0.21, 'Facturas recibidas'!T2:T150, "<>Alquiler de local comercial sujeto a retención") | H3: Incluye Amazon neto de notas de crédito, Amazon Ads España, Eurogrow, IONOS, Finetwork, Digi, Navapack, PlasticForte, Leroy Merlin, portes 21% de Ricardo Terán y facturas mixtas
A4: Operaciones sin IVA / exentas | B4: Cuotas autónomos, seguros y facturas 0% a revisar | C4: =SUMIFS('Facturas recibidas'!K2:K150, 'Facturas recibidas'!X2:X150, "Sí", 'Facturas recibidas'!L2:L150, 0.0) | D4: 0 | E4: =SUMIFS('Facturas recibidas'!M2:M150, 'Facturas recibidas'!X2:X150, "Sí", 'Facturas recibidas'!L2:L150, 0.0) | F4: 0 | G4: =SUMIFS('Facturas recibidas'!N2:N150, 'Facturas recibidas'!X2:X150, "Sí", 'Facturas recibidas'!L2:L150, 0.0) | H4: TGSS, comunidades, seguros préstamo, seguro coche, Amazon 0% y servicios sin IVA; revisar deducibilidad e ISP
A5: Intracomunitarias bienes | B5: ARTEVASI Portugal y VIVEIROS CULTIFLOR con IVA 0, inversión sujeto pasivo | C5: =SUMIFS('Facturas recibidas'!K2:K150, 'Facturas recibidas'!X2:X150, "Sí", 'Facturas recibidas'!T2:T150, "Operación intracomunitaria con inversión sujeto pasivo") | D5: 0.21 | E5: 0 | F5: =C5*0.21 | G5: 851.43 | H5: IVA devengado y deducible estimado al 21% si procede; confirmar tipo español aplicable a cada mercancía
A6: Servicios intracomunitarios | B6: Amazon Ads Italia/Francia y Stripe Irlanda con reverse charge | C6: =SUMIFS('Facturas recibidas'!K2:K150, 'Facturas recibidas'!X2:X150, "Sí", 'Facturas recibidas'!T2:T150, "Servicio intracomunitario con inversión sujeto pasivo") | D6: 0.21 | E6: 0 | F6: =C6*0.21 | G6: 69.82 | H6: Reverse charge estimado; Stripe tiene NIF cliente no informado, revisar cuenta fiscal
A7: IVA nacional 10% | B7: Suministros/mercancías al 10% incluidos en 2T | C7: =SUMIFS('Facturas recibidas'!K2:K150, 'Facturas recibidas'!X2:X150, "Sí", 'Facturas recibidas'!L2:L150, 0.10) | D7: 0.1 | E7: =SUMIFS('Facturas recibidas'!M2:M150, 'Facturas recibidas'!X2:X150, "Sí", 'Facturas recibidas'!L2:L150, 0.10) | F7: 0 | G7: =SUMIFS('Facturas recibidas'!N2:N150, 'Facturas recibidas'!X2:X150, "Sí", 'Facturas recibidas'!L2:L150, 0.10) | H7: Iberdrola, Siro, Projar y Ricardo Terán; revisar afectación/deducibilidad
A8: Servicios no UE / ISP pendiente | B8: Mentoring AMZ Group LLC - Club TPP Elite | C8: =SUMIFS('Facturas recibidas'!K2:K150, 'Facturas recibidas'!X2:X150, "Sí", 'Facturas recibidas'!T2:T150, "Servicio de proveedor no UE sin IVA español") | D8: 0.21 | E8: 0 | F8: =C8*0.21 | G8: 100 | H8: No se incorpora como IVA soportado definitivo hasta revisar inversión sujeto pasivo/afectación
A9: Importaciones/servicios fuera UE | B9: Alibaba/Wuhan China | C9: =SUMIFS('Facturas recibidas'!K2:K150, 'Facturas recibidas'!X2:X150, "Sí", 'Facturas recibidas'!T2:T150, "Compra exterior sin IVA español") | D9: 0 | E9: 0 | F9: 0 | G9: 632.02 | H9: Pendiente DUA, justificante de pago y conversión EUR
A10: Fuera de periodo 2T | B10: Documentos de enero, febrero y marzo | C10: =SUMIFS('Facturas recibidas'!K2:K150, 'Facturas recibidas'!X2:X150, "No") | E10: =SUMIFS('Facturas recibidas'!M2:M150, 'Facturas recibidas'!X2:X150, "No") | G10: =SUMIFS('Facturas recibidas'!N2:N150, 'Facturas recibidas'!X2:X150, "No") | H10: No incluir en 2T salvo corrección/criterio de devengo/caja distinto

Sheet Alertas y revisión
A1: Severidad | B1: Documento | C1: Fecha | D1: Proveedor | E1: Alerta | F1: Acción recomendada | G1: Estado
A2: Alta | B2: CN20260507ES | C2: 46149 | D2: WUHAN BOSA SHIPPING CO., LTD | E2: Importe en USD sin conversión a EUR y sin IVA/DUA claro | F2: Solicitar justificante de pago, tipo de cambio aplicado y documentación de importación/DUA si existe. | G2: Pendiente
A3: Alta | B3: LX2251204 | C3: 46028 | D3: JINHUA LANXIANG IMPORT & EXPORT CO., LTD | E3: Documento fuera de 2T y compra exterior EXW sin DUA/IVA importación | F3: No incluir en 2T; revisar 1T y documentación aduanera/pago. | G3: Pendiente
A4: Media | B4: FA 2026/11490 | C4: 46129 | D4: ARTEVASI, S.A. | E4: Factura UE con IVA 0 por exención RITI | F4: Comprobar alta ROI/VIES y autorrepercusión en modelo 303 si procede. | G4: Pendiente
A5: Media | B5: 729324MTPA26 / 765354G5PA26 / 963144G5PA26 | C5: 46175 | D5: Amazon Online Italy/France | E5: Servicios intracomunitarios Amazon Ads con reverse charge | F5: Comprobar ROI/VIES, autorrepercusión y deducción en modelo 303. | G5: Pendiente
A6: Media | B6: 8489491A-0017 | C6: 46147 | D6: MENTORING AMZ GROUP LLC | E6: Servicio de proveedor EE.UU. sin IVA | F6: Revisar si procede inversión del sujeto pasivo por servicio no UE y afectación a actividad. | G6: Pendiente
A7: Media | B7: Adeudo seguro 08/04/2026 | C7: 46120 | D7: Mutua Madrileña Automovilista | E7: Seguro de coche sin factura fiscal completa/posible afectación parcial | F7: Solicitar póliza/recibo y confirmar uso del vehículo en la actividad antes de deducir. | G7: Pendiente
A8: Media | B8: ES-AEU-2026-320887 / ES-AEU-2026-463539 | C8: 46173 | D8: Amazon EU S.à r.l., Sucursal en España | E8: Facturas Amazon al 0% con referencias LIVA art. 69, 21.5º y 64 | F8: Revisar tratamiento fiscal, deducibilidad y casillas/modelo antes de declarar. | G8: Pendiente
A9: Baja | B9: Notas de crédito Amazon | C9: 46173 | D9: Amazon EU S.à r.l., Sucursal en España | E9: Notas de crédito que minoran base e IVA soportado | F9: Comprobar que se imputan al periodo 2T y enlazan con facturas originales indicadas. | G9: Pendiente
A10: Media | B10: Facturas con IVA mixto | C10: 46148 | D10: PROJAR / RICARDO TERÁN | E10: Facturas con partidas al 10% y 21% | F10: Se han desglosado en IVA por tipos; comprobar que el programa contable admite líneas separadas. | G10: Revisado
A11: Baja | B11: Todos | D11: ANA BELEN FEIJOO VIDUEIRA | E11: No se han aportado facturas emitidas | F11: Añadir facturas emitidas/ventas del cliente para calcular IVA repercutido e ingresos del trimestre. | G11: Pendiente
A12: Baja | B12: Secuencia documental | D12: ANA BELEN FEIJOO VIDUEIRA | E12: No se han aportado documentos 045, 054 y 055 en este bloque | F12: Mantener huecos de numeración o renumerar solo si la gestoría lo prefiere. | G12: Informativo
A13: Media | B13: CU2024252668 / CU2024261474 | C13: 46168 | D13: COMPRAS SEGURAS 2015 S.L.U. - Eurogrow | E13: Compra de vermiculita y artículos promocionales; afectación a actividad no acreditada en factura | F13: Confirmar relación con actividad económica y deducibilidad. | G13: Pendiente
A14: Media | B14: CNP2600738822 / 21260327010178060 | C14: 46108 | D14: Finetwork / Iberdrola | E14: Documentos emitidos antes de abril o de periodos previos incluidos en lote 2T | F14: No incluir en 2T salvo criterio fiscal distinto; revisar si aplica criterio de caja. | G14: Pendiente
A15: Alta | B15: CNP2601150107 / 21260430010173606 / 21260529010183856 | C15: 46171 | D15: Finetwork / Iberdrola | E15: Telecomunicaciones y electricidad en domicilio: deducibilidad y porcentaje de afectación a revisar | F15: Solicitar criterio de afectación, metros declarados o uso profesional antes de deducir IVA/IRPF al 100%. | G15: Pendiente
A16: Media | B16: Comunidad 065-066 | C16: 46174 | D16: CDAD PROP CAMINO CANEIRO 12 | E16: Justificantes bancarios de comunidad, sin factura con IVA | F16: Confirmar afectación del inmueble a la actividad y deducibilidad del gasto. | G16: Pendiente
A17: Media | B17: CNP2602186099 | C17: 46204 | D17: Finetwork | E17: Factura emitida en julio pero referida al consumo de junio | F17: Confirmar criterio de imputación al 2T antes de presentar el Modelo 303. | G17: Pendiente
A18: Media | B18: 1179317G5PA26 / 879336MTPA26 | C18: 46205 | D18: Amazon Ads FR/IT | E18: Servicios intracomunitarios con reverse charge y periodo que cruza 2T/3T | F18: Revisar ROI/VIES, autorrepercusión y prorrateo si se decide imputar parcialmente. | G18: Pendiente
A19: Media | B19: 864039MUPA26 | C19: 46205 | D19: Amazon Online Spain | E19: Publicidad España emitida 02/07 con periodo 27/06-02/07 | F19: Revisar imputación temporal; en este cálculo se incluye por petición del cliente. | G19: Pendiente
A20: Baja | B20: 065-080 | D20: ANA BELEN FEIJOO VIDUEIRA | E20: Se han añadido 16 documentos nuevos al cálculo 2T | F20: Revisar que no existan duplicados con libros previos antes de importar a programa contable. | G20: Informativo
A21: Media | B21: CNP2600738822 / 21260327010178060 | C21: 46108 | D21: Finetwork / Iberdrola | E21: Documentos emitidos antes de abril o de periodos previos incluidos en lote 2T | F21: No incluir en 2T salvo criterio fiscal distinto; revisar si aplica criterio de caja. | G21: Pendiente
A22: Media | B22: CNP2600738822 / 21260327010178060 | C22: 46108 | D22: Finetwork / Iberdrola | E22: Documentos emitidos antes de abril o de periodos previos incluidos en lote 2T | F22: No incluir en 2T salvo criterio fiscal distinto; revisar si aplica criterio de caja. | G22: Pendiente
A23: Nuevo lote 081-089 | B23: Facturas Cultiflor duplicadas | C23: Solo se ha añadido una vez la factura FTRWE 125SEC426/71, pese a haberse subido duplicada. | D23: Media | E23: Revisar que no se duplique en el libro definitivo | F23: Pendiente | G23: 089
A24: Nuevo lote 081-089 | B24: Stripe sin NIF cliente informado | C24: La factura de Stripe indica Customer NIF Number Not Provided. | D24: Media | E24: Corregir datos fiscales en Stripe si procede y confirmar ISP | F24: Pendiente | G24: 086
A25: Nuevo lote 081-089 | B25: Seguros préstamo | C25: Existen justificantes bancarios, no factura con desglose; sin IVA. | D25: Media | E25: Confirmar afectación del préstamo a la actividad antes de deducir en IRPF | F25: Pendiente | G25: 083-085
A26: Nuevo lote 081-089 | B26: Viveiros Portugal | C26: Facturas exentas art. 14 RITI; se ha estimado ISP al 21%, pero el tipo español aplicable debe confirmarse. | D26: Alta | E26: Revisar tipo IVA español por producto antes de presentar modelo 303 | F26: Pendiente | G26: 088-089
A27: Nuevo lote 081-089 | B27: TPP EE.UU. | C27: Servicio de proveedor no UE sin IVA; posible inversión del sujeto pasivo. | D27: Media | E27: Confirmar afectación a actividad y casilla de ISP no UE | F27: Pendiente | G27: 087

Sheet Preparación de modelos
A1: Preparación de modelos fiscales - 2T 2026
A3: Modelo | B3: Concepto | C3: Importe/Base EUR | D3: IVA/Retención EUR | E3: Criterio | F3: Estado
A4: 303 | B4: IVA soportado deducible nacional 21% | C4: ='IVA por tipos'!C3 + 280.00 | D4: ='IVA por tipos'!E3 + 58.80 | E4: Facturas recibidas nacionales con IVA 21% incluidas en 2T, netas de notas de crédito y con nuevas facturas añadidas 081-089 | F4: Preparado con salvedades
A5: 303 | B5: IVA soportado nacional 10% | C5: ='IVA por tipos'!C7 | D5: ='IVA por tipos'!E7 | E5: Iberdrola, Siro, Projar y Ricardo Terán. Revisar afectación/deducibilidad antes de declarar. | F5: Pendiente de revisión
A6: 303 | B6: Base adquisiciones intracomunitarias de bienes | C6: ='IVA por tipos'!C5 | D6: ='IVA por tipos'!F5 | E6: ARTEVASI Portugal y VIVEIROS CULTIFLOR. Revisar ROI/VIES, tipo de IVA español aplicable y casillas exactas del modelo. | F6: Pendiente de revisión
A7: 303 | B7: IVA devengado por inversión sujeto pasivo intracomunitaria estimado | C7: ='IVA por tipos'!C5 | D7: ='IVA por tipos'!F5 | E7: Base intracomunitaria bienes x 21% estimado. Simétricamente deducible si procede. | F7: Pendiente de revisión
A8: 303 | B8: Servicios intracomunitarios recibidos | C8: ='IVA por tipos'!C6 | D8: ='IVA por tipos'!F6 | E8: Amazon Ads Italia/Francia y Stripe Irlanda con reverse charge. Revisar imputación temporal y NIF fiscal en Stripe. | F8: Pendiente de revisión
A9: 303 | B9: Servicio no UE TPP / posible ISP | C9: ='IVA por tipos'!C8 | D9: ='IVA por tipos'!F8 | E9: Proveedor EE.UU. sin IVA; incluye TPP 0017 y 0018. Revisar si procede inversión sujeto pasivo y afectación a actividad. | F9: Pendiente de revisión
A10: 303 | B10: Importaciones / proveedor China | C10: ='IVA por tipos'!C9 | E10: No hay base EUR ni DUA suficiente para incorporar IVA de importación. | F10: Pendiente de documentación
A11: 390 | B11: Resumen anual IVA | C11: 0 | E11: Usar acumulado anual; este Excel solo cubre lote 2T con algunos documentos fuera de periodo. | F11: Informativo
A12: 111 | B12: Retenciones profesionales/trabajo | C12: =SUMIFS('Facturas recibidas'!K2:K150, 'Facturas recibidas'!X2:X150, "Sí", 'Facturas recibidas'!T2:T150, "Retenciones profesionales") | D12: =SUMIFS('Facturas recibidas'!S2:S150, 'Facturas recibidas'!X2:X150, "Sí", 'Facturas recibidas'!T2:T150, "Retenciones profesionales") | E12: No se detectan retenciones en documentos aportados. | F12: Sin importes
A13: 115 | B13: Retenciones alquileres | C13: =SUMIFS('Facturas recibidas'!K2:K150, 'Facturas recibidas'!X2:X150, "Sí", 'Facturas recibidas'!T2:T150, "Alquiler de local comercial sujeto a retención") | D13: =SUMIFS('Facturas recibidas'!S2:S150, 'Facturas recibidas'!X2:X150, "Sí", 'Facturas recibidas'!T2:T150, "Alquiler de local comercial sujeto a retención") | E13: No se detectan alquileres sujetos a retención en los documentos aportados. | F13: Preparado

Sheet Documentos procesados
A1: Nº | B1: Archivo | C1: Fecha documento | D1: Documento | E1: Proveedor | F1: Cliente/NIF | G1: Importe principal | H1: Moneda | I1: Estado | J1: Notas
A2: 1 | B2: 001_2T 2026_ALIBABA-COMPRA BOLSAS PARA CHALECOS.pdf | C2: 46028 | D2: LX2251204 | E2: JINHUA LANXIANG IMPORT & EXPORT CO., LTD | F2: ANA BELEN FEIJOO VIDUEIRA / 34975084L | G2: 997.27 | H2: USD | I2: Pendiente de revisión | J2: Importe EUR indicado como pagado en el documento. Falta DUA/IVA importación y tipo de cambio justificativo.
A3: 2 | B3: 002_2T 2026_Alibaba-Envio Chalecos+Cubre motos-Ana Feijoo---2026.05.03.pdf | C3: 46149 | D3: CN20260507ES | E3: WUHAN BOSA SHIPPING CO., LTD | F3: ANA BELEN FEIJOO VIDUEIRA / 34975084L | G3: 2718.1 | H3: USD | I3: Pendiente de revisión | J3: Falta conversión EUR, factura/justificante de pago y posible tratamiento de importación/DUA por condición DDP.
A4: 3 | B4: 003_2T 2026_ARTEVASI FA_2026_11490.pdf | C4: 46129 | D4: FA 2026/11490 | E4: ARTEVASI, S.A. | F4: ANA BELEN FEIJOO VIDUEIRA / 34975084L | G4: 333.36 | H4: EUR | I4: Pendiente de revisión | J4: Proveedor UE con IVA 0. Requiere autorrepercusión y deducción si procede; base a declarar en operaciones intracomunitarias.
A5: 4 | B5: 004_2T 2026_AUCTANE ES26FC02107187.pdf | C5: 46119 | D5: ES26FC02107187 | E5: AUCTANE S.L.U | F5: ANA BELEN FEIJOO VIDUEIRA / 34975084L | G5: 5.92 | H5: EUR | I5: Revisado | J5: Factura española con IVA 21%.
A6: 5 | B6: 005_2T 2026_Autonomos Abril.pdf | C6: 46142 | D6: Adeudo TGSS 04/2026 | E6: TGSS - R.E. Autónomos | F6: ANA BELEN FEIJOO VIDUEIRA / 34975084L | G6: 299.57 | H6: EUR | I6: Revisado | J6: Cargo bancario de cuota de autónomos; sin IVA.
A7: 6 | B7: 006_2T 2026_Autonomos Mayo.pdf | C7: 46171 | D7: Adeudo TGSS 05/2026 | E7: TGSS - R.E. Autónomos | F7: ANA BELEN FEIJOO VIDUEIRA / 34975084L | G7: 299.57 | H7: EUR | I7: Revisado | J7: Cargo bancario de cuota de autónomos; sin IVA.
A8: 7 | B8: 007_2T 2026_CHATGPT FERBERO Invoice-BIZPYPT5-0010.pdf | C8: 46081 | D8: BIZPYPT5-0010 | E8: OpenAI Ireland Limited | F8: ANA BELEN FEIJOO VIDUEIRA / 34975084L | G8: 19.01 | H8: EUR | I8: Fuera de periodo 2T | J8: Factura 0% reverse charge. Pertenece a febrero, no a 2T.
A9: 8 | B9: 008_2T 2026_CHATGPT Invoice-FDE174A8-0028.pdf | C9: 46079 | D9: FDE174A8-0028 | E9: OpenAI OpCo, LLC | F9: ANA BELEN FEIJOO VIDUEIRA / 34975084L | G9: 20.51 | H9: USD | I9: Fuera de periodo 2T | J9: Base EUR calculada como IVA EUR / 21% porque solo consta IVA en euros. Revisar soporte de pago/tipo cambio.
A10: 9 | B10: 009_2T 2026_CHATGPT Invoice-FDE174A8-0029.pdf | C10: 46107 | D10: FDE174A8-0029 | E10: OpenAI OpCo, LLC | F10: ANA BELEN FEIJOO VIDUEIRA / 34975084L | G10: 20.97 | H10: USD | I10: Fuera de periodo 2T | J10: Base EUR calculada como IVA EUR / 21% porque solo consta IVA en euros. Revisar soporte de pago/tipo cambio.
A11: 10 | B11: 010_2T 2026_CIFRA CE261701849.pdf | C11: 46143 | D11: CE261701849 | E11: C.I.F.R.A., S.L. | F11: ANA BELEN FEIJOO VIDUEIRA / 34975084L | G11: 642.51 | H11: EUR | I11: Revisado | J11: Factura nacional con IVA 21%.
A12: 11 | B12: 011_2T 2026_CIFRA CE261704792.pdf | C12: 46156 | D12: CE261704792 | E12: C.I.F.R.A., S.L. | F12: ANA BELEN FEIJOO VIDUEIRA / 34975084L | G12: 642.51 | H12: EUR | I12: Revisado | J12: Factura nacional con IVA 21%.
A13: 12 | B13: 012_2T 2026_CIFRA CE261708106.pdf | C13: 46169 | D13: CE261708106 | E13: C.I.F.R.A., S.L. | F13: ANA BELEN FEIJOO VIDUEIRA / 34975084L | G13: 642.51 | H13: EUR | I13: Revisado | J13: Factura nacional con IVA 21%.
... A122: 122 | B122: ES-CN-AEU-2026-155131.pdf | C122: 46203 | D122: ES-CN-AEU-2026-155131 | E122: Amazon EU S.à r.l., Sucursal en España | F122: ANA BELEN FEIJOO VIDUEIRA / 34975084L | G122: -3.85 | H122: EUR | I122: Revisado | J122: Nota de crédito de tarifas de logística de Amazon exenta.

Sheet Resumen añadidos 065-080
A1: Resumen de documentos añadidos al cálculo - Ana Belén Feijoo - 2T 2026
A3: Nº | B3: Fecha | C3: Documento | D3: Proveedor | E3: Base EUR | F3: IVA EUR | G3: Total EUR | H3: Tratamiento
A4: 65 | B4: 46146 | C4: R-26-000117/1 | D4: CDAD PROP CAMINO CANEIRO 12 | E4: 140 | F4: 0 | G4: 140 | H4: Gasto sin IVA / comunidad
A5: 66 | B5: 46174 | C5: R-26-000143/1 | D5: CDAD PROP CAMINO CANEIRO 12 | E5: 132 | F5: 0 | G5: 132 | H5: Gasto sin IVA / comunidad
A6: 67 | B6: 46196 | C6: DGFC2617513172 | D6: DIGI Spain Telecom, S.A.U. | E6: 2.67 | F6: 0.56 | G6: 3.23 | H6: Gasto con IVA soportado nacional
A7: 68 | B7: 46189 | C7: CU2024268240 | D7: COMPRAS SEGURAS 2015 S.L.U. / Eurogrow | E7: 54.03 | F7: 11.35 | G7: 65.38 | H7: Compra/gasto con IVA soportado nacional
A8: 69 | B8: 46199 | C8: Q 14190 | D8: FASAWORLD S.L. / Quecartucho | E8: 50.7 | F8: 10.65 | G8: 61.35 | H8: Gasto con IVA soportado nacional
A9: 70 | B9: 46143 | C9: CNP2601497180 | D9: WEWI MOBILE S.L. / Finetwork | E9: 35.29 | F9: 7.41 | G9: 42.7 | H9: Gasto con IVA soportado nacional
A10: 71 | B10: 46174 | C10: CNP2601864214 | D10: WEWI MOBILE S.L. / Finetwork | E10: 32.14 | F10: 6.75 | G10: 38.89 | H10: Gasto con IVA soportado nacional
A11: 72 | B11: 46204 | C11: CNP2602186099 | D11: WEWI MOBILE S.L. / Finetwork | E11: 32.14 | F11: 6.75 | G11: 38.89 | H11: Gasto con IVA soportado nacional
A12: 73 | B12: 46199 | C12: 202786679384 | D12: IONOS Cloud S.L.U. | E12: 8.5 | F12: 1.79 | G12: 10.29 | H12: Gasto con IVA soportado nacional
A13: 74 | B13: 46193 | C13: 058-0006-952306 | D13: Leroy Merlin España S.L.U. | E13: 24.63 | F13: 5.17 | G13: 29.8 | H13: Gasto con IVA soportado nacional
A14: 75 | B14: 46192 | C14: #TI669004776 | D14: Navaprint Gráficas, S.L. / Navapack | E14: 108 | F14: 22.68 | G14: 130.68 | H14: Gasto con IVA soportado nacional
A15: 76 | B15: 46198 | C15: 26213314 | D15: ALBERO FORTE COMPOSITE, S.L.U. / PlasticForte | E15: 514.79 | F15: 108.11 | G15: 622.9 | H15: Compra de mercancía con IVA soportado nacional
... A19: 80 | B19: 46205 | C19: 879336MTPA26 | D19: Amazon Online Italy S.R.L. | E19: 3.61 | F19: 0 | G19: 3.61 | H19: Servicio intracomunitario con inversión sujeto pasivo
A21: Totales añadidos | E21: Base EUR | F21: IVA soportado | G21: Total EUR | H21: Observaciones
A22: Nacional 21% | E22: 1477.42 | F22: 310.27 | G22: 1787.69 | H22: Incluye telecomunicaciones, mercancía, publicidad Amazon España, servicios digitales y compras nacionales
A23: Sin IVA / comunidad | E23: 272 | F23: 0 | G23: 272 | H23: Comunidad de propietarios; revisar afectación/deducibilidad
A24: Servicios intracomunitarios | E24: 27.48 | F24: 0 | G24: 27.48 | H24: Amazon Ads Francia/Italia; reverse charge estimado en modelo 303
A25: ISP estimado servicios intracomunitarios | F25: 5.77 | H25: IVA devengado/deducible estimado al 21% si procede

Sheet Resumen añadidos 081-089
A1: Resumen de documentos añadidos al cálculo - Ana Belén Feijoo - 2T 2026
A3: Nº | B3: Fecha | C3: Documento | D3: Proveedor | E3: Base EUR | F3: IVA EUR | G3: Total EUR | H3: Tratamiento
A4: 81 | B4: 46183 | C4: WB/1368 | D4: RICARDO TERÁN, S.L. | E4: 64.64 | F4: 7.67 | G4: 72.31 | H4: Factura mixta: 10% mercancía y 21% portes
A5: 82 | B5: 46196 | C5: WB/1385 | D5: RICARDO TERÁN, S.L. | E5: 71.46 | F5: 8.36 | G5: 79.82 | H5: Factura mixta: 10% mercancía y 21% portes
A6: 83 | B6: 46118 | C6: BBVA PLAN ESTARSEGURO ABRIL | D6: BBVA / Plan EstarSeguro | E6: 42.46 | F6: 0 | G6: 42.46 | H6: Seguro/préstamo sin IVA, pendiente deducibilidad
A7: 84 | B7: 46148 | C7: BBVA PLAN ESTARSEGURO MAYO | D7: BBVA / Plan EstarSeguro | E7: 42.46 | F7: 0 | G7: 42.46 | H7: Seguro/préstamo sin IVA, pendiente deducibilidad
A8: 85 | B8: 46177 | C8: BBVA PLAN ESTARSEGURO JUNIO | D8: BBVA / Plan EstarSeguro | E8: 42.41 | F8: 0 | G8: 42.41 | H8: Seguro/préstamo sin IVA, pendiente deducibilidad
A9: 86 | B9: 46173 | C9: PQAPRKNC-2026-05 | D9: Stripe Payments Europe, Limited | E9: 1.01 | F9: 0 | G9: 1.01 | H9: Servicio intracomunitario; ISP estimada 21%
A10: 87 | B10: 46178 | C10: 8489491A-0018 | D10: MENTORING AMZ GROUP LLC | E10: 25 | F10: 0 | G10: 25 | H10: Servicio no UE; ISP pendiente de revisión
A11: 88 | B11: 46122 | C11: FTRWE 125SEC426/35 | D11: VIVEIROS CULTIFLOR | E11: 33.91 | F11: 0 | G11: 33.91 | H11: Adquisición intracomunitaria bienes; ISP estimada
A12: 89 | B12: 46190 | C12: FTRWE 125SEC426/71 | D12: VIVEIROS CULTIFLOR | E12: 77.72 | F12: 0 | G12: 77.72 | H12: Adquisición intracomunitaria bienes; añadida una sola vez por duplicado
A14: Totales añadidos | E14: Base EUR | F14: IVA soportado | G14: Total EUR | H14: Observaciones
A15: Nacional 21% | E15: 22 | F15: 4.62 | G15: 26.62 | H15: Portes Ricardo Terán al 21%
A16: Nacional 10% | E16: 114.1 | F16: 11.41 | G16: 125.51 | H16: Mercancía Ricardo Terán al 10%
A17: Sin IVA / seguros | E17: 127.33 | F17: 0 | G17: 127.33 | H17: Seguros préstamo; revisar deducibilidad
A18: Intracomunitarios bienes | E18: 111.63 | F18: 0 | G18: 111.63 | H18: Viveiros Cultiflor; ISP estimada 23,44 € al 21%
A19: Servicios UE/no UE | E19: 26.01 | F19: 0 | G19: 26.01 | H19: Stripe Irlanda y TPP EE.UU.; ISP estimada 5,46 €
